Workbook

Sheet Listas
A1: Dimensão | B1: Disciplinas | C1: Impacto | D1: Gravidade | E1: Abrangência | F1: Recorrente | G1: Tensões | R1: Disciplinas DE | S1: Disciplinas PARA | T1: Detalhe
A2: Diagnóstico e Benchmarking | B2: Maturidade atual | C2: Previsibilidade de Prazo e Entrega | D2: 1 - Baixo (Pontual / Localizado) | E2: Local | F2: Sim | G2: Estrutural | R2: Governança e Gestão de Portfólio | S2: Gestão de Portfólio e Ciclo de Vida | T2: FEL, Ciclo de Vida, Maturidade de Engenharia, Planejamento Físico, Econômico, Financeiro, Gestão de Riscos
A3: Estrutura Organizacional e Governança | B3: Benchmark interno | C3: Eficiência e Controle de Capital | D3: 2 - Moderado (Afeta eficiência) | E3: Multi-Projeto | F3: Não | G3: Processual | R3: Planejamento e Controle Integrado | S3: Gestão de Portfólio e Ciclo de Vida | T3: FEL, Ciclo de Vida, Maturidade de Engenharia, Planejamento Físico, Econômico, Financeiro, Gestão de Riscos
A4: Metodologias e Engenharia de Valor | B4: Benchmark externo | C4: Qualidade da Tomada de Decisão de Investimentos | D4: 3 - Relevante (Afeta previsibilidade) | E4: Organizacional | G4: Informacional | R4: Estimativas e Gestão de Custos | S4: Gestão de Portfólio e Ciclo de Vida | T4: FEL, Ciclo de Vida, Maturidade de Engenharia, Planejamento Físico, Econômico, Financeiro, Gestão de Riscos
A5: Gestão Contratual e Contingências | B5: Boas práticas e referências | C5: Efetividade da Governança de CAPEX | D5: 4 - Alto (Impacto estrutural) | E5: Sistêmico | G5: Técnica | R5: Gestão Contratual e Riscos | S5: Administração Contratual | T5: Administração Contratual, Medições, Pleitos
A6: Gestão de Portfólio e PMO | B6: Lacunas e oportunidades | C6: Eficiência Operacional da Execução | D6: 5 - Crítico (Risco sistêmico) | G6: Financeira | R6: Gestão Contratual e Riscos | S6: Gestão de Portfólio e Ciclo de Vida | T6: FEL, Ciclo de Vida, Maturidade de Engenharia, Planejamento Físico, Econômico, Financeiro, Gestão de Riscos
A7: Tecnologia, Dados e Sistemas | B7: Modelo organizacional | C7: Exposição a Riscos de Investimento | G7: Incentivos e Cultura | R7: Governança Técnica e Engenharia | S7: Engenharia de Valor
A8: Maturidade Técnica e Engenharia | B8: Papéis e responsabilidades | C8: Qualidade Técnica e Maturidade de Engenharia | G8: Capacidade | R8: Suprimentos e Estratégia de Contratação
B9: Alçadas e decisões | C9: Performance Contratual e Cadeia de Fornecimento | R9: Tecnologia, Dados e Sistemas
B10: Comitês e fóruns | C10: Confiabilidade da Informação e Suporte à Decisão | R10: Organização, Cultura e Modelo Operacional
B11: Capacidade e competências | T11: Comitê de CapEx
B12: Ritos e Fluxo de Governança | T12: Suprimentos
B13: Metodologia de gestão CAPEX | T13: Gestão de Conhecimento
B14: Padrões e templates | T14: Papéis, Responsabilidades e Alçadas
B15: Gestão do conhecimento | E15: 1️⃣ Local / Pontual
B16: Engenharia de valor | E16: Um projeto específico
B17: Critérios de avaliação e priorização técnica | E17: Uma equipe específica
B18: Administração contratual | E18: Um contrato específico
B19: Pleitos e aditivos | E19: Sem impacto estruturante no portfólio.
B20: Conformidade contratual | E20: 2️⃣ Multi-Projeto
B21: Política de contingências | E21: Mais de um projeto
B22: Exposição financeira | E22: Uma plataforma
B23: Integração com áreas corporativas | E23: Uma carteira específica
B24: Governança de portfólio | E24: Impacta eficiência, mas não toda a empresa.
B25: Priorização e pipeline | E25: 3️⃣ Organizacional
B26: Ciclo de vida e gates | E26: Afeta:
... B37: Rastreabilidade da informação | E37: Impacto transversal e estratégico.

Sheet Estrutura TOR
A1: # TOR | B1: TOR | C1: Dimensões | D1: Disciplinas
A2: 3.1 | B2: Avaliação e Benchmarking | C2: Diagnóstico e Benchmarking | D2: Maturidade atual; Benchmark interno; Benchmark externo; Boas práticas e referências; Lacunas e oportunidades
A3: 3.2 | B3: Estrutura matricial, papéis, processos e responsabilidades | C3: Estrutura e Governança do CAPEX | D3: Modelo organizacional; Papéis e responsabilidades; Alçadas e decisões; Comitês e fóruns; Capacidade e competências
A4: 3.3 | B4: Padronização de metodologias e gestão do conhecimento | C4: Metodologias e Engenharia de Valor | D4: Metodologia de gestão CAPEX; Padrões e templates ;Gestão do conhecimento; Engenharia de valor ;Critérios de avaliação e priorização técnica
A5: 3.4 | B5: Governança da Administração Contratual | C5: Gestão Contratual e Contingências | D5: Administração contratual; Pleitos e aditivos; Conformidade contratual; Política de contingências; Exposição financeira e uso de contingência
A6: 3.5 | B6: Engenharia de Valor em nível corporativo e de projetos | C6: Metodologias e Engenharia de Valor | D6: Metodologia de gestão CAPEX; Padrões e templates ;Gestão do conhecimento; Engenharia de valor ;Critérios de avaliação e priorização técnica
A7: 3.6 | B7: Governança de contingências de CAPEX | C7: Gestão Contratual e Contingências | D7: Administração contratual; Pleitos e aditivos; Conformidade contratual; Política de contingências; Exposição financeira e uso de contingência
A8: 3.7 | B8: Gestão do portfólio de investimentos | C8: Gestão de Portfólio e PMO | D8: Governança de portfólio; Priorização e pipeline; Ciclo de vida e gates; PMO corporativo e plataformas; Monitoramento físico-financeiro; Indicadores e reports executivos
A9: 3.8 | B9: Escritório de Projetos (corporativo e por plataforma) | C9: Gestão de Portfólio e PMO | D9: Governança de portfólio; Priorização e pipeline; Ciclo de vida e gates; PMO corporativo e plataformas; Monitoramento físico-financeiro; Indicadores e reports executivos
A10: 3.9 | B10: Modelo de governança e integração de sistemas e dados | C10: Tecnologia, Dados e Sistemas | D10: Arquitetura de sistemas; Integração entre sistemas; Modelo e governança de dados; Reports e dashboards; Rastreabilidade da informação
A11: 3.10 | B11: Comitê de CAPEX e Governança Decisória | C11: Estrutura e Governança do CAPEX | D11: Modelo organizacional; Papéis e responsabilidades; Alçadas e decisões; Comitês e fóruns; Capacidade e competências
A12: 3.11 | B12: Competências, cargos e capacidade do Núcleo | C12: Estrutura e Governança do CAPEX | D12: Modelo organizacional; Papéis e responsabilidades; Alçadas e decisões; Comitês e fóruns; Capacidade e competências

Sheet Estrutura TOR2
A1: # TOR | B1: TOR | C1: Dimensões | D1: Disciplinas | E1: Detalhamento
A2: 3.1 | B2: Avaliação e Benchmarking | C2: Diagnóstico e Benchmarking | D2: Maturidade atual | E2: Avaliação do nível atual de governança e gestão de CAPEX
A3: 3.1 | B3: Avaliação e Benchmarking | C3: Diagnóstico e Benchmarking | D3: Benchmark interno | E3: Comparação entre plataformas (ex.: Trilhos × Rodovias)
A4: 3.1 | B4: Avaliação e Benchmarking | C4: Diagnóstico e Benchmarking | D4: Benchmark externo | E4: Referências de mercado e boas práticas
A5: 3.1 | B5: Avaliação e Benchmarking | C5: Diagnóstico e Benchmarking | D5: Boas práticas e referências | E5: Identificação de modelos de governança e gestão aplicáveis
A6: 3.1 | B6: Avaliação e Benchmarking | C6: Diagnóstico e Benchmarking | D6: Lacunas e oportunidades | E6: Principais gaps estruturais identificados
A7: 3.2 | B7: Estrutura matricial, papéis, processos e responsabilidades | C7: Estrutura Organizacional e Governança do CAPEX | D7: Modelo organizacional | E7: Estrutura do Núcleo, posicionamento organizacional e interfaces
A8: 3.2 | B8: Estrutura matricial, papéis, processos e responsabilidades | C8: Estrutura Organizacional e Governança do CAPEX | D8: Papéis e responsabilidades | E8: Distribuição de responsabilidades entre áreas e funções
A9: 3.2 | B9: Estrutura matricial, papéis, processos e responsabilidades | C9: Estrutura Organizacional e Governança do CAPEX | D9: Alçadas e decisões | E9: Matriz decisória, critérios por valor, prazo e criticidade
A10: 3.2 | B10: Estrutura matricial, papéis, processos e responsabilidades | C10: Estrutura Organizacional e Governança do CAPEX | D10: Comitês e fóruns | E10: Estrutura e funcionamento dos fóruns decisórios e Comitê de CAPEX
A11: 3.2 | B11: Estrutura matricial, papéis, processos e responsabilidades | C11: Estrutura Organizacional e Governança do CAPEX | D11: Capacidade e competências | E11: Dimensionamento do Núcleo, perfis profissionais e competências
A12: 3.2 | B12: Estrutura matricial, papéis, processos e responsabilidades | C12: Estrutura Organizacional e Governança do CAPEX | D12: Ritos e Fluxo de Governança | E12: Funcionamento dos fóruns, rituais e fluxos decisórios para avaliação e aprovação de investimentos de CAPEX.
... A68: 3.11 | B68: Competências, cargos e capacidade do Núcleo | C68: Estrutura Organizacional e Governança do CAPEX | D68: Ritos e Fluxo de Governança | E68: Funcionamento dos fóruns, rituais e fluxos decisórios para avaliação e aprovação de investimentos de CAPEX.

Sheet Estrutura
A1: Estrutura completa do diagnóstico
A2: Nível 1 — Evidência Literal
A3: Trecho literal da entrevista
A4: "Cada área aprova projetos de um jeito diferente."
A6: Nível 2 — Problema estrutural
A7: Interpretação analítica da evidência
A8: Ausência de padronização na governança decisória de investimentos
A10: Nível 3 — Dimensão
A11: Framework atual
A12: Estrutura Organizacional e Governança do CAPEX
A14: Nível 4 — Disciplina
A15: Onde o problema ocorre
... A23: Quantas entrevistas citaram o mesmo problema

Sheet Taxonomias
A1: Dimensão | B1: Definição
A2: Estrutura Organizacional e Governança do CAPEX | B2: Definição do modelo organizacional do Núcleo de CAPEX, incluindo papéis, responsabilidades, alçadas decisórias, fóruns de governança e fluxos de decisão que suportam a gestão dos investimentos.
A3: Metodologias e Engenharia de Valor | B3: Estrutura metodológica utilizada para gestão de projetos de CAPEX, incluindo padronização de processos, templates, gestão do conhecimento e aplicação de práticas de engenharia de valor para otimização técnica e econômica dos projetos.
A4: Gestão Contratual e Contingências | B4: Estrutura de governança e gestão do ciclo contratual do CAPEX, incluindo administração de contratos, gestão de pleitos e aditivos, conformidade contratual, política de contingências e monitoramento de exposição financeira.
A5: Gestão de Portfólio e PMO | B5: Estrutura de governança responsável pela seleção, priorização, acompanhamento e controle do portfólio de investimentos, incluindo atuação do PMO, monitoramento físico-financeiro, indicadores executivos e gestão de riscos do portfólio.
A6: Tecnologia, Dados e Sistemas | B6: Estrutura de sistemas, governança de dados e ferramentas analíticas utilizadas para suportar a gestão do CAPEX, garantindo integração de informações, confiabilidade de dados, rastreabilidade e suporte à tomada de decisão.
A8: Disciplina | B8: Definição
A9: Maturidade atual | B9: Avaliação do nível atual de governança e gestão do CAPEX na organização.
A10: Benchmark interno | B10: Comparação de práticas entre plataformas ou áreas da organização.
A11: Benchmark externo | B11: Comparação com práticas de mercado e referências de gestão de CAPEX.
A12: Boas práticas e referências | B12: Identificação de práticas consolidadas e modelos de referência utilizados na gestão de CAPEX.
A13: Lacunas e oportunidades | B13: Identificação de lacunas estruturais e oportunidades de evolução na gestão do CAPEX.
... A55: Confiabilidade da Informação e Suporte à Decisão | B55: Impactos na qualidade, rastreabilidade e disponibilidade de dados e sistemas para gestão e tomada de decisão.

Sheet  Lista de Entrevistas
A1: entrevista_id | B1: Nome | C1: Cargo | D1: Diretoria | E1: Plataforma | F1: Área | G1: Nível | H1: Data | I1: Entrevista
A2: 1 | B2: Paulo Cesar Martins Amaral | C2: =VLOOKUP($B2,'Lista de Entrevistas_BD'!$D$2:$M$121,4,FALSE) -> Consultor Contratos Implantação | D2: =VLOOKUP($B2,'Lista de Entrevistas_BD'!$D$2:$M$121,5,FALSE) -> VP Trilhos | E2: =VLOOKUP($B2,'Lista de Entrevistas_BD'!$D$2:$M$121,7,FALSE) -> Trilhos | F2: Administração Contratual | G2: Operacional | H2: =VLOOKUP($B2,'Lista de Entrevistas_BD'!$D$2:$M$121,8,FALSE) -> 46073.375 | I2: Coleta de Dados
A3: 2 | B3: Paulo Henrique de Almeida Aredes | C3: =VLOOKUP($B3,'Lista de Entrevistas_BD'!$D$2:$M$121,4,FALSE) -> Consultor Contratos Implantação (L4) | D3: =VLOOKUP($B3,'Lista de Entrevistas_BD'!$D$2:$M$121,5,FALSE) -> VP Trilhos | E3: =VLOOKUP($B3,'Lista de Entrevistas_BD'!$D$2:$M$121,7,FALSE) -> Trilhos | F3: Contratos e Riscos | G3: Operacional | H3: =VLOOKUP($B3,'Lista de Entrevistas_BD'!$D$2:$M$121,8,FALSE) -> 46073.438 | I3: Coleta de Dados
A4: 3 | B4: Rodrigo Correa de Souza | C4: =VLOOKUP($B4,'Lista de Entrevistas_BD'!$D$2:$M$121,4,FALSE) -> Consultor Engenharia | D4: =VLOOKUP($B4,'Lista de Entrevistas_BD'!$D$2:$M$121,5,FALSE) -> VP Trilhos | E4: =VLOOKUP($B4,'Lista de Entrevistas_BD'!$D$2:$M$121,7,FALSE) -> Trilhos | F4: Engenharia de Implantação / Qualidade | G4: Operacional | H4: =VLOOKUP($B4,'Lista de Entrevistas_BD'!$D$2:$M$121,8,FALSE) -> 46073.562 | I4: Coleta de Dados
A5: 4 | B5: Rodrigo Mitsuo Kise | C5: =VLOOKUP($B5,'Lista de Entrevistas_BD'!$D$2:$M$121,4,FALSE) -> Gerente Executivo Empreedimentos e PMO - Projetos Técnicos (L4) | D5: =VLOOKUP($B5,'Lista de Entrevistas_BD'!$D$2:$M$121,5,FALSE) -> VP Trilhos | E5: =VLOOKUP($B5,'Lista de Entrevistas_BD'!$D$2:$M$121,7,FALSE) -> Trilhos | F5: Gestão de Capex / Projetos | G5: Tático | H5: =VLOOKUP($B5,'Lista de Entrevistas_BD'!$D$2:$M$121,8,FALSE) -> 46073.625 | I5: Coleta de Dados
A6: 5 | B6: Emilio Simon Povoa | C6: =VLOOKUP($B6,'Lista de Entrevistas_BD'!$D$2:$M$121,4,FALSE) -> Gerente Executivo Gerenciamento de Riscos | D6: =VLOOKUP($B6,'Lista de Entrevistas_BD'!$D$2:$M$121,5,FALSE) -> VP Trilhos | E6: =VLOOKUP($B6,'Lista de Entrevistas_BD'!$D$2:$M$121,7,FALSE) -> Trilhos | F6: Engenharia de Implantação | G6: Tático | H6: =VLOOKUP($B6,'Lista de Entrevistas_BD'!$D$2:$M$121,8,FALSE) -> 46073.708 | I6: Coleta de Dados
A7: 6 | B7: Vanilza de Souza Pandolfo | C7: =VLOOKUP($B7,'Lista de Entrevistas_BD'!$D$2:$M$121,4,FALSE) -> Consultora Riscos Engenharia | D7: =VLOOKUP($B7,'Lista de Entrevistas_BD'!$D$2:$M$121,5,FALSE) -> VP Trilhos | E7: =VLOOKUP($B7,'Lista de Entrevistas_BD'!$D$2:$M$121,7,FALSE) -> Trilhos | F7: Gestão de Riscos de Projetos | G7: Operacional | H7: =VLOOKUP($B7,'Lista de Entrevistas_BD'!$D$2:$M$121,8,FALSE) -> 46076.438 | I7: Coleta de Dados
A8: 7 | B8: William Nascimento Marins | C8: =VLOOKUP($B8,'Lista de Entrevistas_BD'!$D$2:$M$121,4,FALSE) -> Gerente de PMO | D8: =VLOOKUP($B8,'Lista de Entrevistas_BD'!$D$2:$M$121,5,FALSE) -> VP Trilhos | E8: =VLOOKUP($B8,'Lista de Entrevistas_BD'!$D$2:$M$121,7,FALSE) -> Trilhos | F8: PMO / Demais Empreendimentos | G8: Tático | H8: =VLOOKUP($B8,'Lista de Entrevistas_BD'!$D$2:$M$121,8,FALSE) -> 46076.583 | I8: Coleta de Dados
A9: 8 | B9: Michel Simoes Araujo | C9: =VLOOKUP($B9,'Lista de Entrevistas_BD'!$D$2:$M$121,4,FALSE) -> Gerente Executivo Acompanhamento de Projetos | D9: =VLOOKUP($B9,'Lista de Entrevistas_BD'!$D$2:$M$121,5,FALSE) -> VP Trilhos | E9: =VLOOKUP($B9,'Lista de Entrevistas_BD'!$D$2:$M$121,7,FALSE) -> Trilhos | F9: Capex / Engenharia | G9: Tático | H9: =VLOOKUP($B9,'Lista de Entrevistas_BD'!$D$2:$M$121,8,FALSE) -> 46076.646 | I9: Coleta de Dados
A10: 9 | B10: Jean Carlos Bonin da Silva | C10: =VLOOKUP($B10,'Lista de Entrevistas_BD'!$D$2:$M$121,4,FALSE) -> Coordenador PMO | D10: =VLOOKUP($B10,'Lista de Entrevistas_BD'!$D$2:$M$121,5,FALSE) -> VP Trilhos | E10: =VLOOKUP($B10,'Lista de Entrevistas_BD'!$D$2:$M$121,7,FALSE) -> Trilhos | F10: Planejamento / PMO | G10: Operacional | H10: =VLOOKUP($B10,'Lista de Entrevistas_BD'!$D$2:$M$121,8,FALSE) -> 46077.458 | I10: Coleta de Dados
A11: 10 | B11: Rebeka Yang Wang | C11: =VLOOKUP($B11,'Lista de Entrevistas_BD'!$D$2:$M$121,4,FALSE) -> Coordenadora PMO | D11: =VLOOKUP($B11,'Lista de Entrevistas_BD'!$D$2:$M$121,5,FALSE) -> VP Trilhos | E11: =VLOOKUP($B11,'Lista de Entrevistas_BD'!$D$2:$M$121,7,FALSE) -> Trilhos | F11: PMO Engenharia Trilhos | G11: Operacional | H11: =VLOOKUP($B11,'Lista de Entrevistas_BD'!$D$2:$M$121,8,FALSE) -> 46077.562 | I11: Coleta de Dados
A12: 11 | B12: Ricardo Alexandre Benicio | C12: =VLOOKUP($B12,'Lista de Entrevistas_BD'!$D$2:$M$121,4,FALSE) -> Diretor Engenharia de Manutenção | D12: =VLOOKUP($B12,'Lista de Entrevistas_BD'!$D$2:$M$121,5,FALSE) -> VP Trilhos | E12: =VLOOKUP($B12,'Lista de Entrevistas_BD'!$D$2:$M$121,7,FALSE) -> Trilhos | F12: Engenharia de Operação e Manutenção / Expansão Linha 4 | G12: Estratégico | H12: =VLOOKUP($B12,'Lista de Entrevistas_BD'!$D$2:$M$121,8,FALSE) -> 46077.688 | I12: Coleta de Dados
A13: 12 | B13: Elmo Serejo Pithon Copello | C13: =VLOOKUP($B13,'Lista de Entrevistas_BD'!$D$2:$M$121,4,FALSE) -> Gerente Engenharia Empreedimentos | D13: =VLOOKUP($B13,'Lista de Entrevistas_BD'!$D$2:$M$121,5,FALSE) -> VP Trilhos | E13: =VLOOKUP($B13,'Lista de Entrevistas_BD'!$D$2:$M$121,7,FALSE) -> Trilhos | F13: Projetos – Demais Empreendimentos | G13: Tático | H13: =VLOOKUP($B13,'Lista de Entrevistas_BD'!$D$2:$M$121,8,FALSE) -> 46078.646 | I13: Coleta de Dados
... A18: 17 | B18: Danieli Patricia Ribeiro | C18: =VLOOKUP($B18,'Lista de Entrevistas_BD'!$D$2:$M$121,4,FALSE) -> Assessora Projetos Corporativos | D18: =VLOOKUP($B18,'Lista de Entrevistas_BD'!$D$2:$M$121,5,FALSE) -> VP Financeiro e Relações Investidores | E18: =VLOOKUP($B18,'Lista de Entrevistas_BD'!$D$2:$M$121,7,FALSE) -> Corporativo | F18: Assessora Projetos Corporativos | G18: Estratégico | H18: =VLOOKUP($B18,'Lista de Entrevistas_BD'!$D$2:$M$121,8,FALSE) -> 46084.625 | I18: Coleta de Dados
A19: 18 | B19: Guilherme Tellis | C19: =VLOOKUP($B19,'Lista de Entrevistas_BD'!$D$2:$M$121,4,FALSE) -> Especialista de PMO | D19: =VLOOKUP($B19,'Lista de Entrevistas_BD'!$D$2:$M$121,5,FALSE) -> VP Trilhos | E19: =VLOOKUP($B19,'Lista de Entrevistas_BD'!$D$2:$M$121,7,FALSE) -> Trilhos | H19: =VLOOKUP($B19,'Lista de Entrevistas_BD'!$D$2:$M$121,8,FALSE) -> 46080.583 | I19: Coleta de Dados
A20: 19 | B20: Juliana Magalhaes Vasconcelos Salomao | C20: =VLOOKUP($B20,'Lista de Entrevistas_BD'!$D$2:$M$121,4,FALSE) -> Gerente Gestão Fornecedores e Sustentação | D20: =VLOOKUP($B20,'Lista de Entrevistas_BD'!$D$2:$M$121,5,FALSE) -> VP Financeiro e Relações Investidores | E20: =VLOOKUP($B20,'Lista de Entrevistas_BD'!$D$2:$M$121,7,FALSE) -> Corporativo | F20: Sustentação | G20: Estratégico | H20: =VLOOKUP($B20,'Lista de Entrevistas_BD'!$D$2:$M$121,8,FALSE) -> 46084.562 | I20: Coleta de Dados
A21: 20 | B21: Gustavo Henrique Lucas Jaquie | C21: =VLOOKUP($B21,'Lista de Entrevistas_BD'!$D$2:$M$121,4,FALSE) -> Gerente Executivo Engenharia Projetos e Centro Expertise | D21: =VLOOKUP($B21,'Lista de Entrevistas_BD'!$D$2:$M$121,5,FALSE) -> VP Trilhos | E21: =VLOOKUP($B21,'Lista de Entrevistas_BD'!$D$2:$M$121,7,FALSE) -> Trilhos | H21: =VLOOKUP($B21,'Lista de Entrevistas_BD'!$D$2:$M$121,8,FALSE) -> 46072.583 | I21: Coleta de Dados
A22: 21 | B22: Afranio Nogueira Magalhaes | C22: =VLOOKUP($B22,'Lista de Entrevistas_BD'!$D$2:$M$121,4,FALSE) -> Gerente Executivo Engenharia e Obras | D22: =VLOOKUP($B22,'Lista de Entrevistas_BD'!$D$2:$M$121,5,FALSE) -> VP Rodovias | E22: =VLOOKUP($B22,'Lista de Entrevistas_BD'!$D$2:$M$121,7,FALSE) -> Rodovias | H22: =VLOOKUP($B22,'Lista de Entrevistas_BD'!$D$2:$M$121,8,FALSE) -> 46100.458 | I22: Coleta de Dados
A23: 22 | B23: Alexandre Fontes Pereira | C23: =VLOOKUP($B23,'Lista de Entrevistas_BD'!$D$2:$M$121,4,FALSE) -> Gerente Executivo PMO, Qualidade e Riscos | D23: =VLOOKUP($B23,'Lista de Entrevistas_BD'!$D$2:$M$121,5,FALSE) -> VP Rodovias | E23: =VLOOKUP($B23,'Lista de Entrevistas_BD'!$D$2:$M$121,7,FALSE) -> Rodovias | H23: =VLOOKUP($B23,'Lista de Entrevistas_BD'!$D$2:$M$121,8,FALSE) -> 46097.583 | I23: Coleta de Dados
A24: 23 | B24: Ana Laura Marocolo Marigo | C24: =VLOOKUP($B24,'Lista de Entrevistas_BD'!$D$2:$M$121,4,FALSE) -> Coordenadora PMO | D24: =VLOOKUP($B24,'Lista de Entrevistas_BD'!$D$2:$M$121,5,FALSE) -> VP Rodovias | E24: =VLOOKUP($B24,'Lista de Entrevistas_BD'!$D$2:$M$121,7,FALSE) -> Rodovias | H24: =VLOOKUP($B24,'Lista de Entrevistas_BD'!$D$2:$M$121,8,FALSE) -> 46099.375 | I24: Coleta de Dados
A25: 24 | B25: Anderson Aparecido Zanetti | C25: =VLOOKUP($B25,'Lista de Entrevistas_BD'!$D$2:$M$121,4,FALSE) -> Consultor PMO | D25: =VLOOKUP($B25,'Lista de Entrevistas_BD'!$D$2:$M$121,5,FALSE) -> VP Rodovias | E25: =VLOOKUP($B25,'Lista de Entrevistas_BD'!$D$2:$M$121,7,FALSE) -> Rodovias | H25: =VLOOKUP($B25,'Lista de Entrevistas_BD'!$D$2:$M$121,8,FALSE) -> 46098.417 | I25: Coleta de Dados
A26: 25 | B26: Cesar Sampaio de Castro | C26: =VLOOKUP($B26,'Lista de Entrevistas_BD'!$D$2:$M$121,4,FALSE) -> Gerente Gestão Portfólio e Valor | D26: =VLOOKUP($B26,'Lista de Entrevistas_BD'!$D$2:$M$121,5,FALSE) -> VP Inovação, Tecnologia e Riscos | E26: =VLOOKUP($B26,'Lista de Entrevistas_BD'!$D$2:$M$121,7,FALSE) -> Corporativo | H26: =VLOOKUP($B26,'Lista de Entrevistas_BD'!$D$2:$M$121,8,FALSE) -> 46099.625 | I26: Coleta de Dados
A27: 26 | B27: Heloisa Helena de Oliveira Tormin Chaer | C27: =VLOOKUP($B27,'Lista de Entrevistas_BD'!$D$2:$M$121,4,FALSE) -> Gerente Executiva Planejamento e Governança | D27: =VLOOKUP($B27,'Lista de Entrevistas_BD'!$D$2:$M$121,5,FALSE) -> VP Inovação, Tecnologia e Riscos | E27: =VLOOKUP($B27,'Lista de Entrevistas_BD'!$D$2:$M$121,7,FALSE) -> Corporativo | H27: =VLOOKUP($B27,'Lista de Entrevistas_BD'!$D$2:$M$121,8,FALSE) -> 46097.688 | I27: Coleta de Dados
A28: 27 | B28: Jaime Marlon Silva | C28: =VLOOKUP($B28,'Lista de Entrevistas_BD'!$D$2:$M$121,4,FALSE) -> Gerente Executivo Soluções Engenharia e Logística | D28: =VLOOKUP($B28,'Lista de Entrevistas_BD'!$D$2:$M$121,5,FALSE) -> VP Inovação, Tecnologia e Riscos | E28: =VLOOKUP($B28,'Lista de Entrevistas_BD'!$D$2:$M$121,7,FALSE) -> Corporativo | H28: =VLOOKUP($B28,'Lista de Entrevistas_BD'!$D$2:$M$121,8,FALSE) -> 46097.583 | I28: Coleta de Dados
A29: 28 | B29: Jorge Rangel Maia | C29: =VLOOKUP($B29,'Lista de Entrevistas_BD'!$D$2:$M$121,4,FALSE) -> Gerente Executivo Suprimentos Mobilidade e Aero | D29: =VLOOKUP($B29,'Lista de Entrevistas_BD'!$D$2:$M$121,5,FALSE) -> VP Financeiro e Relações Investidores | E29: =VLOOKUP($B29,'Lista de Entrevistas_BD'!$D$2:$M$121,7,FALSE) -> Corporativo | H29: =VLOOKUP($B29,'Lista de Entrevistas_BD'!$D$2:$M$121,8,FALSE) -> 46098.583 | I29: Coleta de Dados
A30: 29 | B30: Jorge Manuel Goncalves Pereira | C30: =VLOOKUP($B30,'Lista de Entrevistas_BD'!$D$2:$M$121,4,FALSE) -> Gerente Executivo Estratégia de Operações | D30: =VLOOKUP($B30,'Lista de Entrevistas_BD'!$D$2:$M$121,5,FALSE) -> VP Rodovias | E30: =VLOOKUP($B30,'Lista de Entrevistas_BD'!$D$2:$M$121,7,FALSE) -> Rodovias | H30: =VLOOKUP($B30,'Lista de Entrevistas_BD'!$D$2:$M$121,8,FALSE) -> 46099.583 | I30: Coleta de Dados
A31: 30 | B31: Juliana Ming Martini Naressi | C31: =VLOOKUP($B31,'Lista de Entrevistas_BD'!$D$2:$M$121,4,FALSE) -> Coordenador Compras Sustentáveis | D31: =VLOOKUP($B31,'Lista de Entrevistas_BD'!$D$2:$M$121,5,FALSE) -> VP Financeiro e Relações Investidores | E31: =VLOOKUP($B31,'Lista de Entrevistas_BD'!$D$2:$M$121,7,FALSE) -> Corporativo | H31: =VLOOKUP($B31,'Lista de Entrevistas_BD'!$D$2:$M$121,8,FALSE) -> 46100.583 | I31: Coleta de Dados
A32: 31 | B32: Karina Baungartner | C32: =VLOOKUP($B32,'Lista de Entrevistas_BD'!$D$2:$M$121,4,FALSE) -> Gerente PMO Rodovias | D32: =VLOOKUP($B32,'Lista de Entrevistas_BD'!$D$2:$M$121,5,FALSE) -> VP Rodovias | E32: =VLOOKUP($B32,'Lista de Entrevistas_BD'!$D$2:$M$121,7,FALSE) -> Rodovias | H32: =VLOOKUP($B32,'Lista de Entrevistas_BD'!$D$2:$M$121,8,FALSE) -> 46098.396 | I32: Coleta de Dados
... A65: 64 | B65: Flavia Godoy de Carvalho E Silva | C65: =VLOOKUP($B65,'Lista de Entrevistas_BD'!$D$2:$M$121,4,FALSE) -> Diretora de Relação Investidores | D65: =VLOOKUP($B65,'Lista de Entrevistas_BD'!$D$2:$M$121,5,FALSE) -> VP Financeiro e Relações Investidores | E65: =VLOOKUP($B65,'Lista de Entrevistas_BD'!$D$2:$M$121,7,FALSE) -> Corporativo | H65: =VLOOKUP($B65,'Lista de Entrevistas_BD'!$D$2:$M$121,8,FALSE) -> 46112.583 | I65: Coleta de Dados
A66: 65 | B66: Jean Carlos Bonin da Silva - A | C66: Coordenador PMO | D66: VP Trilhos | E66: Trilhos | F66: Planejamento / PMO | G66: Operacional | H66: 46107 | I66: Aprofundamento
A67: 66 | B67: Lucas Giraldi Rapchan Aguilar - A | C67: Gerente PMO Rodovias | D67: VP Rodovias | E67: Rodovias | H67: 46104 | I67: Aprofundamento
A68: 67 | B68: Guilherme Tellis - A | C68: Especialista de PMO | D68: VP Trilhos | E68: Trilhos | H68: 46085 | I68: Aprofundamento
A69: 68 | B69: Tiago Terra Esteves - A | C69: =VLOOKUP($B69,'Lista de Entrevistas_BD'!$D$2:$M$121,4,FALSE) -> #N/A | D69: =VLOOKUP($B69,'Lista de Entrevistas_BD'!$D$2:$M$121,5,FALSE) -> #N/A | E69: Trilhos | H69: 46106 | I69: Aprofundamento
A70: 69 | B70: Vinicius Vancellote - A | C70: Especialista de PMO | D70: VP Trilhos | E70: Trilhos | F70: PMO - Demais Empreendimentos | H70: 46112 | I70: Aprofundamento

Sheet Analise Individual
A1: entrevista_id | B1: Entrevistado | C1: Nível | D1: Plataforma | E1: Diretoria | F1: Gerência Executiva | G1: Evidência Literal | H1: Problema Estrutural | I1: Dimensão | J1: Disciplina | K1: Impacto | L1: Abrangência | M1: Recorrente
A2: 16 | B2: Adriana Martins dos Santos | D2: Trilhos | G2: “Suprimentos atende sob demanda. Mas como a gente faz assim, que suprimentos realmente viva o dia a dia do negócio, não necessariamente ando dentro do negócio, não é isso não.” | H2: Contratações sem planejamento e escopo maturado | I2: Planejamento e Baseline | J2: Suprimentos e Estratégia de Contratação | K2: Contratos e Cadeia de Fornecimento | L2: Multi-Projeto | M2: Sim
A3: 16 | B3: Adriana Martins dos Santos | D3: Trilhos | G3: “Suprimentos atende sob demanda. Mas como a gente faz assim, que suprimentos realmente viva o dia a dia do negócio, não necessariamente ando dentro do negócio, não é isso não.” | H3: Contratações sem planejamento e escopo maturado | I3: Planejamento e Baseline | J3: Suprimentos e Estratégia de Contratação | K3: Prazo e Confiabilidade do Cronograma | L3: Multi-Projeto | M3: Sim
A4: 16 | B4: Adriana Martins dos Santos | D4: Trilhos | G4: “Suprimentos atende sob demanda. Mas como a gente faz assim, que suprimentos realmente viva o dia a dia do negócio, não necessariamente ando dentro do negócio, não é isso não.” | H4: Contratações sem planejamento e escopo maturado | I4: Planejamento e Baseline | J4: Suprimentos e Estratégia de Contratação | K4: Custos e Contingências | L4: Multi-Projeto | M4: Sim
A5: 16 | B5: Adriana Martins dos Santos | D5: Trilhos | G5: “Eu não transfiro gestão contratual de nenhum contrato de Capex para a operação ou para manutenção.” | H5: Governança de custos e contingências insuficiente | I5: Custos e contingências | J5: Estimativas e Gestão de Custos | K5: Custos e Contingências | L5: Organizacional | M5: Sim
A6: 16 | B6: Adriana Martins dos Santos | D6: Trilhos | G6: “Eu não transfiro gestão contratual de nenhum contrato de Capex para a operação ou para manutenção.” | H6: Governança de custos e contingências insuficiente | I6: Custos e contingências | J6: Estimativas e Gestão de Custos | K6: Governança e Performance do Portfólio | L6: Organizacional | M6: Sim
A7: 16 | B7: Adriana Martins dos Santos | D7: Trilhos | G7: “Eu não transfiro gestão contratual de nenhum contrato de Capex para a operação ou para manutenção.” | H7: Governança de custos e contingências insuficiente | I7: Custos e contingências | J7: Estimativas e Gestão de Custos | K7: Riscos e Incertezas | L7: Organizacional | M7: Sim
A8: 16 | B8: Adriana Martins dos Santos | D8: Trilhos | G8: “Hoje não existe uma integração sistêmica... é um sofrimento que a gente pelo menos acompanha para conseguir as informações.” | H8: Coordenação interáreas insuficiente e decisões ad hoc | I8: Integração Organizacional | J8: Organização, Cultura e Modelo Operacional | K8: Integração Organizacional | L8: Organizacional | M8: Sim
A9: 16 | B9: Adriana Martins dos Santos | D9: Trilhos | G9: “Hoje não existe uma integração sistêmica... é um sofrimento que a gente pelo menos acompanha para conseguir as informações.” | H9: Coordenação interáreas insuficiente e decisões ad hoc | I9: Integração Organizacional | J9: Organização, Cultura e Modelo Operacional | K9: Eficiência Operacional | L9: Organizacional | M9: Sim
A10: 16 | B10: Adriana Martins dos Santos | D10: Trilhos | G10: “Hoje não existe uma integração sistêmica... é um sofrimento que a gente pelo menos acompanha para conseguir as informações.” | H10: Coordenação interáreas insuficiente e decisões ad hoc | I10: Integração Organizacional | J10: Organização, Cultura e Modelo Operacional | K10: Governança e Performance do Portfólio | L10: Organizacional | M10: Sim
A11: 16 | B11: Adriana Martins dos Santos | D11: Trilhos | G11: “Eu não sou surpreendida, AI, eu não sabia, AI tem um aditivo. Então a gente tem processo de gestão de mudança.” | H11: Gestão contratual reativa e com pleitos | I11: Gestão Contratual e Pleitos | J11: Gestão Contratual e Riscos | K11: Contratos e Cadeia de Fornecimento | L11: Multi-Projeto | M11: Sim
A12: 16 | B12: Adriana Martins dos Santos | D12: Trilhos | G12: “Eu não sou surpreendida, AI, eu não sabia, AI tem um aditivo. Então a gente tem processo de gestão de mudança.” | H12: Gestão contratual reativa e com pleitos | I12: Gestão Contratual e Pleitos | J12: Gestão Contratual e Riscos | K12: Custos e Contingências | L12: Multi-Projeto | M12: Sim
A13: 16 | B13: Adriana Martins dos Santos | D13: Trilhos | G13: “Eu não sou surpreendida, AI, eu não sabia, AI tem um aditivo. Então a gente tem processo de gestão de mudança.” | H13: Gestão contratual reativa e com pleitos | I13: Gestão Contratual e Pleitos | J13: Gestão Contratual e Riscos | K13: Prazo e Confiabilidade do Cronograma | L13: Multi-Projeto | M13: Sim
... A427: 7 | B427: William Nascimento Marins | D427: Trilhos | G427: “Não tem uma receita de bolo... até a atividade mãe tem, está nos manuais... o detalhamento depende de experiência.” | H427: Coordenação interáreas insuficiente e decisões ad hoc | I427: Integração Organizacional | J427: Organização, Cultura e Modelo Operacional | K427: Governança e Performance do Portfólio | L427: Organizacional | M427: Sim

Sheet Evidências_Estruturadas
A1: entrevista_id | B1: Plataforma | C1: Diretoria | D1: Gerência Executiva | E1: Disciplina | F1: Evidência Literal | G1: Problema | H1: Impacto | I1: Abrangência | J1: Recorrente
A2: 15 | B2: =VLOOKUP($A2,' Lista de Entrevistas'!$A$1:$I$222,5,FALSE) -> Corporativo | C2: =VLOOKUP($A2,' Lista de Entrevistas'!$A$1:$I$222,4,FALSE) -> VP Financeiro e Relações Investidores | E2: Governança e Gestão de Portfólio | G2: Ausência de padronização no nível de maturidade da Engenharia para contratações de fornecedores | H2: Aumento de Custos
A3: 15 | B3: =VLOOKUP($A3,' Lista de Entrevistas'!$A$1:$I$222,5,FALSE) -> Corporativo | C3: =VLOOKUP($A3,' Lista de Entrevistas'!$A$1:$I$222,4,FALSE) -> VP Financeiro e Relações Investidores | E3: Governança e Gestão de Portfólio | G3: Ausência de padronização no nível de maturidade da Engenharia para contratações de fornecedores | H3: Retrabalho Suprimentos
A4: 15 | B4: =VLOOKUP($A4,' Lista de Entrevistas'!$A$1:$I$222,5,FALSE) -> Corporativo | C4: =VLOOKUP($A4,' Lista de Entrevistas'!$A$1:$I$222,4,FALSE) -> VP Financeiro e Relações Investidores | E4: Governança e Gestão de Portfólio | G4: Ausência de padronização no nível de maturidade da Engenharia para contratações de fornecedores | H4: Retrabalho Engenharia
A5: 15 | B5: =VLOOKUP($A5,' Lista de Entrevistas'!$A$1:$I$222,5,FALSE) -> Corporativo | C5: =VLOOKUP($A5,' Lista de Entrevistas'!$A$1:$I$222,4,FALSE) -> VP Financeiro e Relações Investidores | E5: Governança e Gestão de Portfólio | G5: Ausência de padronização no nível de maturidade da Engenharia para contratações de fornecedores | H5: Impacto de Prazo
A6: 15 | B6: =VLOOKUP($A6,' Lista de Entrevistas'!$A$1:$I$222,5,FALSE) -> Corporativo | C6: =VLOOKUP($A6,' Lista de Entrevistas'!$A$1:$I$222,4,FALSE) -> VP Financeiro e Relações Investidores | E6: Planejamento e Controle Integrado | G6: Falta de visibilidade no planejamento de projetos | H6: Impacto de Prazo
A7: 15 | B7: =VLOOKUP($A7,' Lista de Entrevistas'!$A$1:$I$222,5,FALSE) -> Corporativo | C7: =VLOOKUP($A7,' Lista de Entrevistas'!$A$1:$I$222,4,FALSE) -> VP Financeiro e Relações Investidores | E7: Planejamento e Controle Integrado | G7: Falta de visibilidade no planejamento de projetos | H7: Impacto de Custo
A8: 15 | B8: =VLOOKUP($A8,' Lista de Entrevistas'!$A$1:$I$222,5,FALSE) -> Corporativo | C8: =VLOOKUP($A8,' Lista de Entrevistas'!$A$1:$I$222,4,FALSE) -> VP Financeiro e Relações Investidores | E8: Planejamento e Controle Integrado | G8: Falta de visibilidade no planejamento de projetos | H8: Ausência de Relacionamentos
A9: 15 | B9: =VLOOKUP($A9,' Lista de Entrevistas'!$A$1:$I$222,5,FALSE) -> Corporativo | C9: =VLOOKUP($A9,' Lista de Entrevistas'!$A$1:$I$222,4,FALSE) -> VP Financeiro e Relações Investidores | E9: Tecnologia, Dados e Sistemas | G9: Confiabilidade das informações recebidas | H9: Falta de Confiabilidade
A10: 15 | B10: =VLOOKUP($A10,' Lista de Entrevistas'!$A$1:$I$222,5,FALSE) -> Corporativo | C10: =VLOOKUP($A10,' Lista de Entrevistas'!$A$1:$I$222,4,FALSE) -> VP Financeiro e Relações Investidores | E10: Organização, Cultura e Modelo Operacional | G10: Falta de clareza de papéis e responsabilidades do núcleo de CapEx | H10: Ineficiência por ausência de responsabilidade
A11: 15 | B11: =VLOOKUP($A11,' Lista de Entrevistas'!$A$1:$I$222,5,FALSE) -> Corporativo | C11: =VLOOKUP($A11,' Lista de Entrevistas'!$A$1:$I$222,4,FALSE) -> VP Financeiro e Relações Investidores | E11: Organização, Cultura e Modelo Operacional | G11: Elevada quantidade de iniciativas de transformação | H11: Sobrecarga de recursos
A12: 16 | B12: =VLOOKUP($A12,' Lista de Entrevistas'!$A$1:$I$222,5,FALSE) -> Trilhos | C12: =VLOOKUP($A12,' Lista de Entrevistas'!$A$1:$I$222,4,FALSE) -> VP Trilhos | E12: Organização, Cultura e Modelo Operacional | F12: Suprimentos e financeiro são áreas de apoio, mas não vivem o dia a dia do negócio, o que gera desalinhamento de prioridades e senso de urgência. | G12: Interfaces fracas entre áreas e suportes | H12: Produtividade e retrabalho | I12: Organizacional | J12: Sim
A13: 16 | B13: =VLOOKUP($A13,' Lista de Entrevistas'!$A$1:$I$222,5,FALSE) -> Trilhos | C13: =VLOOKUP($A13,' Lista de Entrevistas'!$A$1:$I$222,4,FALSE) -> VP Trilhos | E13: Organização, Cultura e Modelo Operacional | F13: Suprimentos e financeiro são áreas de apoio, mas não vivem o dia a dia do negócio, o que gera desalinhamento de prioridades e senso de urgência. | G13: Interfaces fracas entre áreas e suportes | H13: Previsibilidade de prazo e marcos | I13: Organizacional | J13: Sim
A14: 16 | B14: =VLOOKUP($A14,' Lista de Entrevistas'!$A$1:$I$222,5,FALSE) -> Trilhos | C14: =VLOOKUP($A14,' Lista de Entrevistas'!$A$1:$I$222,4,FALSE) -> VP Trilhos | E14: Organização, Cultura e Modelo Operacional | F14: Suprimentos atende sob demanda, sem atuação preventiva ou imersão no negócio. | G14: Atuação reativa de áreas de apoio | H14: Previsibilidade de prazo e marcos | I14: Organizacional | J14: Sim
A15: 16 | B15: =VLOOKUP($A15,' Lista de Entrevistas'!$A$1:$I$222,5,FALSE) -> Trilhos | C15: =VLOOKUP($A15,' Lista de Entrevistas'!$A$1:$I$222,4,FALSE) -> VP Trilhos | E15: Organização, Cultura e Modelo Operacional | F15: Suprimentos atende sob demanda, sem atuação preventiva ou imersão no negócio. | G15: Atuação reativa de áreas de apoio | H15: Produtividade e retrabalho | I15: Organizacional | J15: Sim
A16: 16 | B16: =VLOOKUP($A16,' Lista de Entrevistas'!$A$1:$I$222,5,FALSE) -> Trilhos | C16: =VLOOKUP($A16,' Lista de Entrevistas'!$A$1:$I$222,4,FALSE) -> VP Trilhos | E16: Tecnologia, Dados e Sistemas | F16: Consolidação de dados de CAPEX depende de múltiplos sistemas e reconciliações manuais. | G16: Sistemas fragmentados e consolidação manual | H16: Dados, transparência e rastreabilidade | I16: Sistêmico | J16: Sim
A17: 16 | B17: =VLOOKUP($A17,' Lista de Entrevistas'!$A$1:$I$222,5,FALSE) -> Trilhos | C17: =VLOOKUP($A17,' Lista de Entrevistas'!$A$1:$I$222,4,FALSE) -> VP Trilhos | E17: Tecnologia, Dados e Sistemas | F17: Consolidação de dados de CAPEX depende de múltiplos sistemas e reconciliações manuais. | G17: Sistemas fragmentados e consolidação manual | H17: Produtividade e retrabalho | I17: Sistêmico | J17: Sim
A18: 16 | B18: =VLOOKUP($A18,' Lista de Entrevistas'!$A$1:$I$222,5,FALSE) -> Trilhos | C18: =VLOOKUP($A18,' Lista de Entrevistas'!$A$1:$I$222,4,FALSE) -> VP Trilhos | E18: Organização, Cultura e Modelo Operacional | F18: Integração centralizada busca garantir uniformidade, mas há risco de cada vertical operar de forma distinta. | G18: Baixa padronização entre unidades/verticais | H18: Produtividade e retrabalho | I18: Organizacional | J18: Sim
A19: 16 | B19: =VLOOKUP($A19,' Lista de Entrevistas'!$A$1:$I$222,5,FALSE) -> Trilhos | C19: =VLOOKUP($A19,' Lista de Entrevistas'!$A$1:$I$222,4,FALSE) -> VP Trilhos | E19: Organização, Cultura e Modelo Operacional | F19: Suprimentos e financeiro são áreas de apoio, mas não vivem o dia a dia do negócio, o que gera desalinhamento de prioridades e senso de urgência. | G19: Interfaces fracas entre áreas e suportes | H19: Produtividade e retrabalho | I19: Organizacional | J19: Sim
A20: 13 | B20: =VLOOKUP($A20,' Lista de Entrevistas'!$A$1:$I$222,5,FALSE) -> Trilhos | C20: =VLOOKUP($A20,' Lista de Entrevistas'!$A$1:$I$222,4,FALSE) -> VP Trilhos | E20: Organização, Cultura e Modelo Operacional | F20: Relato de conflitos e retrabalho sob modelo matricial anterior, com áreas especializadas atuando de forma pouco integrada. | G20: Integração matricial inefetiva entre áreas | H20: Produtividade e retrabalho | I20: Organizacional | J20: Não
A21: 13 | B21: =VLOOKUP($A21,' Lista de Entrevistas'!$A$1:$I$222,5,FALSE) -> Trilhos | C21: =VLOOKUP($A21,' Lista de Entrevistas'!$A$1:$I$222,4,FALSE) -> VP Trilhos | E21: Organização, Cultura e Modelo Operacional | F21: Relato de conflitos e retrabalho sob modelo matricial anterior, com áreas especializadas atuando de forma pouco integrada. | G21: Integração matricial inefetiva entre áreas | H21: Previsibilidade de prazo e marcos | I21: Organizacional | J21: Não
A22: 13 | B22: =VLOOKUP($A22,' Lista de Entrevistas'!$A$1:$I$222,5,FALSE) -> Trilhos | C22: =VLOOKUP($A22,' Lista de Entrevistas'!$A$1:$I$222,4,FALSE) -> VP Trilhos | E22: Governança Técnica e Engenharia | F22: Tentativa recente de estruturar processos preventivos, mas ainda com lacunas de integração entre áreas (ex: operação/manutenção). | G22: Integração CAPEX-OPEX e requisitos operacionais frágil | H22: Qualidade técnica, construtibilidade e mudanças tardias | I22: Organizacional | J22: Sim
A23: 13 | B23: =VLOOKUP($A23,' Lista de Entrevistas'!$A$1:$I$222,5,FALSE) -> Trilhos | C23: =VLOOKUP($A23,' Lista de Entrevistas'!$A$1:$I$222,4,FALSE) -> VP Trilhos | E23: Governança Técnica e Engenharia | F23: Tentativa recente de estruturar processos preventivos, mas ainda com lacunas de integração entre áreas (ex: operação/manutenção). | G23: Integração CAPEX-OPEX e requisitos operacionais frágil | H23: Previsibilidade de custo e acurácia de estimativas | I23: Organizacional | J23: Sim
... A28: 13 | B28: =VLOOKUP($A28,' Lista de Entrevistas'!$A$1:$I$222,5,FALSE) -> Trilhos | C28: =VLOOKUP($A28,' Lista de Entrevistas'!$A$1:$I$222,4,FALSE) -> VP Trilhos | E28: Organização, Cultura e Modelo Operacional | F28: Mudança para estrutura verticalizada visando autonomia e foco no resultado do empreendimento. | G28: Baixa padronização entre unidades/verticais | H28: Produtividade e retrabalho | I28: Organizacional | J28: Sim

Sheet Referências
A1: Disciplina | B1: Problema estrutural | C1: Descrição do Problema Estrutural | D1: Abrangência | E1: Impactos | F1: Recorrente | G1: Nº Relatórios | H1: Menção Literal (com autor) | I1: Relatórios
A2: Tecnologia, Dados e Sistemas | B2: Sistemas fragmentados e consolidação manual | C2: Múltiplos sistemas não integrados exigem consolidação manual recorrente para reporte e decisão. | D2: Sistêmico | E2: Dados; Produtividade | F2: Sim | G2: 8 | H2: “Múltiplos sistemas não conversam, exigindo tratamento manual.” – Adriana Martins dos Santos “Dependência de repasse de dados para consolidação.” – Rebeka Yang Wang | I2: ANDRE LUIS TEIXEIRA OLIVEIRA FREITAS; Adriana Martins dos Santos; Elmo Serejo Pithon Copello; Guilherme Tellis; Rebeka Yang Wang; Rodrigo Mitsuo Kise; Vanilza de Souza Pandolfo; WILLIAM NASCIMENTO MARINS
A3: Planejamento e Controle Integrado | B3: Controle integrado de prazos insuficiente | C3: Planejamento não estruturado por restrições e baixa integração entre cronograma, execução e controle. | D3: Multi-Projeto | E3: Prazo; Dados | F3: Sim | G3: 5 | H3: “Problemas só são revelados na execução.” – Michel Simoes Araujo “Cumprimento de prazos não é previsível.” – Guilherme Tellis | I3: Guilherme Tellis; Jean Carlos Bonin da Silva; Michel Simoes Araujo; Rodrigo Mitsuo Kise; WILLIAM NASCIMENTO MARINS
A4: Governança Técnica e Engenharia | B4: Integração CAPEX-OPEX e requisitos operacionais frágil | C4: Decisões de investimento não incorporam formalmente critérios operacionais e impacto futuro de OPEX. | D4: Organizacional | E4: Custo; Produtividade; Qualidade Técnica | F4: Sim | G4: 4 | H4: “Trade-off entre CAPEX e OPEX não é estruturado.” – Ricardo Alexandre Pereira Benicio “Operação participa sem critérios formais.” – Elmo Serejo Pithon Copello | I4: ANDRE LUIS TEIXEIRA OLIVEIRA FREITAS; Elmo Serejo Pithon Copello; Ricardo Alexandre Pereira Benicio; Rodrigo Correa de Souza
A5: Organização, Cultura e Modelo Operacional | B5: Interfaces fracas entre áreas e suportes | C5: Falta alinhamento estruturado entre áreas técnicas, operacionais e corporativas, gerando conflito e retrabalho. | D5: Organizacional | E5: Produtividade; Prazo | F5: Sim | G5: 4 | H5: “Conflitos entre diretores impactam projetos.” – Guilherme Tellis “Falhas de comunicação entre áreas.” – Rodrigo Correa de Souza | I5: Adriana Martins dos Santos; Guilherme Tellis; Rebeka Yang Wang; Rodrigo Correa de Souza
A6: Organização, Cultura e Modelo Operacional | B6: Papéis e responsabilidades não definidos | C6: Ausência de delimitação clara de responsabilidades ponta-a-ponta e accountability transversal. | D6: Organizacional | E6: Produtividade; Riscos; Dados | F6: Sim | G6: 3 | H6: “Escopo se mistura.” – Adriana Martins dos Santos “Sem consolidação ou visão integrada.” – Rebeka Yang Wang | I6: Adriana Martins dos Santos; Rebeka Yang Wang; Rodrigo Correa de Souza
A7: Gestão Contratual e Riscos | B7: Governança de riscos e contingências insuficiente | C7: Gestão de riscos não plenamente integrada ao planejamento, orçamento e decisões executivas. | D7: Organizacional | E7: Riscos; Custo; Prazo | F7: Sim | G7: 3 | H7: “Cultura de riscos concentrada na área central.” – Rodrigo Mitsuo Kise “Dependem de validação central.” – WILLIAM NASCIMENTO MARINS | I7: Guilherme Tellis; Rodrigo Mitsuo Kise; WILLIAM NASCIMENTO MARINS
A8: Suprimentos e Estratégia de Contratação | B8: Demanda chega imatura, compras reativas | C8: Projetos chegam à área de compras com baixa maturidade técnica, exigindo atuação emergencial. | D8: Multi-Projeto | E8: Prazo; Contratual; Produtividade | F8: Sim | G8: 2 | H8: “Apagar incêndios.” – Jean Carlos Bonin da Silva “Pouco tempo para negociação.” – Elmo Serejo Pithon Copello | I8: Elmo Serejo Pithon Copello; Jean Carlos Bonin da Silva
A9: Governança e Gestão de Portfólio | B9: Governança de decisão e priorização insuficiente | C9: Processo de priorização de investimentos não institucionalizado com critérios técnicos estruturados. | D9: Organizacional | E9: Portfólio; Prazo; Custo | F9: Sim | G9: 2 | H9: “Cada área defende seu próprio interesse.” – Rodrigo Correa de Souza “Sem filtro técnico.” – Adriana Martins dos Santos | I9: Adriana Martins dos Santos; Rodrigo Correa de Souza

Sheet Nuvem
A1: 1 | B1: Sistemas fragmentados e consolidação manual | C1: Sistemas"Fragmentados"
A2: =A1+1 -> 2 | B2: Sistemas fragmentados e consolidação manual | C2: Sistemas"Fragmentados"
A3: =A2+1 -> 3 | B3: Sistemas fragmentados e consolidação manual | C3: Sistemas"Fragmentados"
A4: =A3+1 -> 4 | B4: Sistemas fragmentados e consolidação manual | C4: Sistemas"Fragmentados"
A5: =A4+1 -> 5 | B5: Sistemas fragmentados e consolidação manual | C5: Sistemas"Fragmentados"
A6: =A5+1 -> 6 | B6: Sistemas fragmentados e consolidação manual | C6: Sistemas"Fragmentados"
A7: =A6+1 -> 7 | B7: Sistemas fragmentados e consolidação manual | C7: Sistemas"Fragmentados"
A8: =A7+1 -> 8 | B8: Sistemas fragmentados e consolidação manual | C8: Sistemas"Fragmentados"
A9: 1 | B9: Controle integrado de prazos insuficiente | C9: Controle"Prazos"Insuficientes
A10: 2 | B10: Controle integrado de prazos insuficiente | C10: Controle"Prazos"Insuficientes
A11: 3 | B11: Controle integrado de prazos insuficiente | C11: Controle"Prazos"Insuficientes
A12: 4 | B12: Controle integrado de prazos insuficiente | C12: Controle"Prazos"Insuficientes
A13: 5 | B13: Controle integrado de prazos insuficiente | C13: Controle"Prazos"Insuficientes
A14: 1 | B14: Integração CAPEX-OPEX e requisitos operacionais frágil | C14: Integração"CapexOpex"
A15: 2 | B15: Integração CAPEX-OPEX e requisitos operacionais frágil | C15: Integração"CapexOpex"
A16: 3 | B16: Integração CAPEX-OPEX e requisitos operacionais frágil | C16: Integração"CapexOpex"
A17: 4 | B17: Integração CAPEX-OPEX e requisitos operacionais frágil | C17: Integração"CapexOpex"
A18: 1 | B18: Interfaces fracas entre áreas e suportes | C18: Interfaces/Áreas
A19: 2 | B19: Interfaces fracas entre áreas e suportes | C19: Interfaces/Áreas
A20: 3 | B20: Interfaces fracas entre áreas e suportes | C20: Interfaces/Áreas
... A27: 3 | B27: Papéis e responsabilidades não definidos | C27: Papeis&Responsabilidades
A28: 1 | B28: Governança de decisão e priorização insuficiente
A29: 2 | B29: Governança de decisão e priorização insuficiente
A30: 1 | B30: Trade-off CAPEX/OPEX sem governança | C30: Governça;Capex/Opex
A31: 2 | B31: Trade-off CAPEX/OPEX sem governança
A32: 1 | B32: Atuação reativa de áreas de apoio
A33: 2 | B33: Atuação reativa de áreas de apoio
A34: 1 | B34: Baixa padronização entre unidades/verticais | C34: Despadronização
A35: 2 | B35: Baixa padronização entre unidades/verticais
A36: 1 | B36: Sequenciamento físico subordinado ao econômico-financeiro
A37: 2 | B37: Sequenciamento físico subordinado ao econômico-financeiro
A38: 1 | B38: Rastreabilidade insuficiente de informações | C38: Rastreabilidade
A39: 2 | B39: Rastreabilidade insuficiente de informações

Sheet Tensões_Estruturais
A1: tema | B1: área_A | C1: área_B | D1: conflito | E1: evidência | F1: tipo de tensão

Sheet Planilha1
A1: entrevista_id | B1: Plataforma | C1: Diretoria | D1: Gerência Executiva | E1: Disciplina | F1: Evidência literal | G1: Problema estrutural | H1: Impacto | I1: Abrangência | J1: Recorrente
A2: Adriana Martins dos Santos | B2: Trilhos | C2: Engenharia e Implantação | D2: Não informado | E2: Organização, Cultura e Modelo Operacional | F2: Suprimentos e financeiro são áreas de apoio, mas não vivem o dia a dia do negócio, o que gera desalinhamento de prioridades e senso de urgência. | G2: Interfaces fracas entre áreas e suportes | H2: Produtividade e retrabalho | I2: Organizacional | J2: Sim
A3: Adriana Martins dos Santos | B3: Trilhos | C3: Engenharia e Implantação | D3: Não informado | E3: Organização, Cultura e Modelo Operacional | F3: Suprimentos e financeiro são áreas de apoio, mas não vivem o dia a dia do negócio, o que gera desalinhamento de prioridades e senso de urgência. | G3: Interfaces fracas entre áreas e suportes | H3: Previsibilidade de prazo e marcos | I3: Organizacional | J3: Sim
A4: Adriana Martins dos Santos | B4: Trilhos | C4: Engenharia e Implantação | D4: Não informado | E4: Organização, Cultura e Modelo Operacional | F4: Suprimentos atende sob demanda, sem atuação preventiva ou imersão no negócio. | G4: Atuação reativa de áreas de apoio | H4: Previsibilidade de prazo e marcos | I4: Organizacional | J4: Sim
A5: Adriana Martins dos Santos | B5: Trilhos | C5: Engenharia e Implantação | D5: Não informado | E5: Organização, Cultura e Modelo Operacional | F5: Suprimentos atende sob demanda, sem atuação preventiva ou imersão no negócio. | G5: Atuação reativa de áreas de apoio | H5: Produtividade e retrabalho | I5: Organizacional | J5: Sim
A6: Adriana Martins dos Santos | B6: Trilhos | C6: Engenharia e Implantação | D6: Não informado | E6: Tecnologia, Dados e Sistemas | F6: Consolidação de dados de CAPEX depende de múltiplos sistemas e reconciliações manuais. | G6: Sistemas fragmentados e consolidação manual | H6: Dados, transparência e rastreabilidade | I6: Sistêmico | J6: Sim
A7: Adriana Martins dos Santos | B7: Trilhos | C7: Engenharia e Implantação | D7: Não informado | E7: Tecnologia, Dados e Sistemas | F7: Consolidação de dados de CAPEX depende de múltiplos sistemas e reconciliações manuais. | G7: Sistemas fragmentados e consolidação manual | H7: Produtividade e retrabalho | I7: Sistêmico | J7: Sim
A8: Adriana Martins dos Santos | B8: Trilhos | C8: Engenharia e Implantação | D8: Não informado | E8: Organização, Cultura e Modelo Operacional | F8: Integração centralizada busca garantir uniformidade, mas há risco de cada vertical operar de forma distinta. | G8: Baixa padronização entre unidades/verticais | H8: Produtividade e retrabalho | I8: Organizacional | J8: Sim
A9: Adriana Martins dos Santos | B9: Trilhos | C9: Engenharia e Implantação | D9: Não informado | E9: Organização, Cultura e Modelo Operacional | F9: Suprimentos e financeiro são áreas de apoio, mas não vivem o dia a dia do negócio, o que gera desalinhamento de prioridades e senso de urgência. | G9: Interfaces fracas entre áreas e suportes | H9: Produtividade e retrabalho | I9: Organizacional | J9: Sim
A10: ANDRE LUIS TEIXEIRA OLIVEIRA FREITAS | B10: Trilhos | C10: Engenharia e Implantação | D10: Não informado | E10: Organização, Cultura e Modelo Operacional | F10: Relato de conflitos e retrabalho sob modelo matricial anterior, com áreas especializadas atuando de forma pouco integrada. | G10: Integração matricial inefetiva entre áreas | H10: Produtividade e retrabalho | I10: Organizacional | J10: Não
A11: ANDRE LUIS TEIXEIRA OLIVEIRA FREITAS | B11: Trilhos | C11: Engenharia e Implantação | D11: Não informado | E11: Organização, Cultura e Modelo Operacional | F11: Relato de conflitos e retrabalho sob modelo matricial anterior, com áreas especializadas atuando de forma pouco integrada. | G11: Integração matricial inefetiva entre áreas | H11: Previsibilidade de prazo e marcos | I11: Organizacional | J11: Não
A12: ANDRE LUIS TEIXEIRA OLIVEIRA FREITAS | B12: Trilhos | C12: Engenharia e Implantação | D12: Não informado | E12: Governança Técnica e Engenharia | F12: Tentativa recente de estruturar processos preventivos, mas ainda com lacunas de integração entre áreas (ex: operação/manutenção). | G12: Integração CAPEX-OPEX e requisitos operacionais frágil | H12: Qualidade técnica, construtibilidade e mudanças tardias | I12: Organizacional | J12: Sim
... A43: Elmo Serejo Pithon Copello | B43: Trilhos | C43: Não informado | D43: Não informado | E43: Governança Técnica e Engenharia | F43: Tentativa recente de estruturar processos preventivos, mas ainda com lacunas de integração entre áreas (ex: operação/manutenção). | G43: Integração CAPEX-OPEX e requisitos operacionais frágil | H43: Produtividade e retrabalho | I43: Organizacional | J43: Sim

Sheet Analise Individual (2)
A1: entrevista_id | B1: entrevistado | C1: nivel | D1: plataforma | E1: evidencia | F1: problema_estrutural | G1: disciplina | H1: dimensao | I1: impacto | J1: abrangencia | K1: recorrente
A2: =_xlfn.XLOOKUP(B2,' Lista de Entrevistas'!B:B,' Lista de Entrevistas'!A:A,"") -> 1 | B2: Paulo Cesar Martins Amaral | C2: Gerência | D2: Trilhos | E2: A administração contratual está sendo estruturada com a bicicleta andando. | F2: Gestão contratual e riscos pulverizada entre áreas | G2: Modelo organizacional | H2: Estrutura Organizacional e Governança do CAPEX | I2: Performance Contratual e Cadeia de Fornecimento | J2: Organizacional | K2: Sim
A3: =_xlfn.XLOOKUP(B3,' Lista de Entrevistas'!B:B,' Lista de Entrevistas'!A:A,"") -> 1 | B3: Paulo Cesar Martins Amaral | C3: Gerência | D3: Trilhos | E3: A administração contratual está sendo estruturada com a bicicleta andando. | F3: Gestão contratual e riscos pulverizada entre áreas | G3: Modelo organizacional | H3: Estrutura Organizacional e Governança do CAPEX | I3: Efetividade da Governança de CAPEX | J3: Organizacional | K3: Sim
A4: =_xlfn.XLOOKUP(B4,' Lista de Entrevistas'!B:B,' Lista de Entrevistas'!A:A,"") -> 1 | B4: Paulo Cesar Martins Amaral | C4: Gerência | D4: Trilhos | E4: Foi necessário difundir cultura de administração contratual e de registro. | F4: Comunicação contratual sem padronização nem controle | G4: Administração contratual | H4: Gestão Contratual e Contingências | I4: Performance Contratual e Cadeia de Fornecimento | J4: Organizacional | K4: Sim
A5: =_xlfn.XLOOKUP(B5,' Lista de Entrevistas'!B:B,' Lista de Entrevistas'!A:A,"") -> 1 | B5: Paulo Cesar Martins Amaral | C5: Gerência | D5: Trilhos | E5: Foi necessário difundir cultura de administração contratual e de registro. | F5: Comunicação contratual sem padronização nem controle | G5: Administração contratual | H5: Gestão Contratual e Contingências | I5: Confiabilidade da Informação e Suporte à Decisão | J5: Organizacional | K5: Sim
A6: =_xlfn.XLOOKUP(B6,' Lista de Entrevistas'!B:B,' Lista de Entrevistas'!A:A,"") -> 1 | B6: Paulo Cesar Martins Amaral | C6: Gerência | D6: Trilhos | E6: Projetos básicos ou sem projeto viraram oportunidades para muitos pleitos. | F6: Termos de referência rasos geram retrabalho contratual | G6: Padrões e templates | H6: Metodologias e Engenharia de Valor | I6: Performance Contratual e Cadeia de Fornecimento | J6: Organizacional | K6: Sim
A7: =_xlfn.XLOOKUP(B7,' Lista de Entrevistas'!B:B,' Lista de Entrevistas'!A:A,"") -> 1 | B7: Paulo Cesar Martins Amaral | C7: Gerência | D7: Trilhos | E7: Projetos básicos ou sem projeto viraram oportunidades para muitos pleitos. | F7: Termos de referência rasos geram retrabalho contratual | G7: Padrões e templates | H7: Metodologias e Engenharia de Valor | I7: Eficiência e Controle de Capital | J7: Organizacional | K7: Sim
A8: =_xlfn.XLOOKUP(B8,' Lista de Entrevistas'!B:B,' Lista de Entrevistas'!A:A,"") -> 2 | B8: Paulo Henrique de Almeida Aredes | C8: Gerência | D8: Trilhos | E8: Governança e burocracias travam o processo de medição e pagamento. | F8: Processos operacionais de pagamento geram atraso aos fornecedores | G8: Administração contratual | H8: Gestão Contratual e Contingências | I8: Performance Contratual e Cadeia de Fornecimento | J8: Organizacional | K8: Sim
A9: =_xlfn.XLOOKUP(B9,' Lista de Entrevistas'!B:B,' Lista de Entrevistas'!A:A,"") -> 2 | B9: Paulo Henrique de Almeida Aredes | C9: Gerência | D9: Trilhos | E9: Governança e burocracias travam o processo de medição e pagamento. | F9: Processos operacionais de pagamento geram atraso aos fornecedores | G9: Administração contratual | H9: Gestão Contratual e Contingências | I9: Previsibilidade de Prazo e Entrega | J9: Organizacional | K9: Sim
A10: =_xlfn.XLOOKUP(B10,' Lista de Entrevistas'!B:B,' Lista de Entrevistas'!A:A,"") -> 2 | B10: Paulo Henrique de Almeida Aredes | C10: Gerência | D10: Trilhos | E10: Quanto mais demora para pagar, mais o fornecedor pequeno é prejudicado. | F10: Fornecedores pequenos não suportam prazos de governança | G10: Exposição financeira | H10: Gestão Contratual e Contingências | I10: Performance Contratual e Cadeia de Fornecimento | J10: Multi-Projeto | K10: Sim
A11: =_xlfn.XLOOKUP(B11,' Lista de Entrevistas'!B:B,' Lista de Entrevistas'!A:A,"") -> 2 | B11: Paulo Henrique de Almeida Aredes | C11: Gerência | D11: Trilhos | E11: Quanto mais demora para pagar, mais o fornecedor pequeno é prejudicado. | F11: Fornecedores pequenos não suportam prazos de governança | G11: Exposição financeira | H11: Gestão Contratual e Contingências | I11: Exposição a Riscos de Investimento | J11: Multi-Projeto | K11: Sim
A12: =_xlfn.XLOOKUP(B12,' Lista de Entrevistas'!B:B,' Lista de Entrevistas'!A:A,"") -> 2 | B12: Paulo Henrique de Almeida Aredes | C12: Gerência | D12: Trilhos | E12: Mesmo com mérito, um pleito pode não ser aceito pelo concedente. | F12: Estratégia de contratação condicionada pelo poder concedente | G12: Integração com áreas corporativas | H12: Gestão Contratual e Contingências | I12: Exposição a Riscos de Investimento | J12: Multi-Projeto | K12: Não
A13: =_xlfn.XLOOKUP(B13,' Lista de Entrevistas'!B:B,' Lista de Entrevistas'!A:A,"") -> 2 | B13: Paulo Henrique de Almeida Aredes | C13: Gerência | D13: Trilhos | E13: Mesmo com mérito, um pleito pode não ser aceito pelo concedente. | F13: Estratégia de contratação condicionada pelo poder concedente | G13: Integração com áreas corporativas | H13: Gestão Contratual e Contingências | I13: Performance Contratual e Cadeia de Fornecimento | J13: Multi-Projeto | K13: Não
... A366: =_xlfn.XLOOKUP(B366,' Lista de Entrevistas'!B:B,' Lista de Entrevistas'!A:A,"") -> 53 | B366: Gabriel Bittencourt Jacondino | C366: Gerência Executiva | D366: Trilhos | E366: “Isso te leva a um sobrecusto que eu não vou conseguir cobrar.” | F366: Escopo excedente gera sobrecusto não recuperável | G366: Exposição financeira | H366: Gestão Contratual e Contingências | I366: Eficiência e Controle de Capital | J366: Multi-Projeto | K366: Sim
A367: =_xlfn.XLOOKUP(B367,' Lista de Entrevistas'!B:B,' Lista de Entrevistas'!A:A,"") -> 54 | B367: Alexandro Marcelo Zopolato Francisco
A368: =_xlfn.XLOOKUP(B368,' Lista de Entrevistas'!B:B,' Lista de Entrevistas'!A:A,"") -> 54 | B368: Alexandro Marcelo Zopolato Francisco | C368: Gerência Executiva | D368: Rodovias | E368: “Eu cuido de todos os investimentos… tenho que explicar custo e prazo.” | F368: Alta dependência de gestão individualizada | G368: Papéis e responsabilidades | H368: Estrutura Organizacional e Governança do CAPEX | I368: Eficiência Operacional da Execução | J368: Organizacional | K368: Sim
A369: =_xlfn.XLOOKUP(B369,' Lista de Entrevistas'!B:B,' Lista de Entrevistas'!A:A,"") -> 54 | B369: Alexandro Marcelo Zopolato Francisco | C369: Gerência Executiva | D369: Rodovias | E369: “Eu geralmente vou sozinho… é muita informação em pouco tempo.” | F369: Capacidade insuficiente para demandas estratégicas | G369: Capacidade e competências | H369: Estrutura Organizacional e Governança do CAPEX | I369: Qualidade da Tomada de Decisão de Investimentos | J369: Organizacional | K369: Sim
A370: =_xlfn.XLOOKUP(B370,' Lista de Entrevistas'!B:B,' Lista de Entrevistas'!A:A,"") -> 54 | B370: Alexandro Marcelo Zopolato Francisco | C370: Gerência Executiva | D370: Rodovias | E370: “A interface é com todos… não tem como fazer nada sozinho.” | F370: Alto grau de dependência de interfaces | G370: Integração com áreas corporativas | H370: Estrutura Organizacional e Governança do CAPEX | I370: Eficiência Operacional da Execução | J370: Organizacional | K370: Sim
A371: =_xlfn.XLOOKUP(B371,' Lista de Entrevistas'!B:B,' Lista de Entrevistas'!A:A,"") -> 54 | B371: Alexandro Marcelo Zopolato Francisco | C371: Gerência Executiva | D371: Rodovias | E371: “Eu não converso com todo mundo… falo com a integradora.” | F371: Dependência de intermediários na gestão | G371: Modelo organizacional | H371: Estrutura Organizacional e Governança do CAPEX | I371: Efetividade da Governança de CAPEX | J371: Organizacional | K371: Sim
A372: =_xlfn.XLOOKUP(B372,' Lista de Entrevistas'!B:B,' Lista de Entrevistas'!A:A,"") -> 54 | B372: Alexandro Marcelo Zopolato Francisco | C372: Gerência Executiva | D372: Rodovias | E372: “Cada obra tinha RDO diferente… não tem padrão.” | F372: Ausência de padronização operacional | G372: Padrões e templates | H372: Metodologias e Engenharia de Valor | I372: Confiabilidade da Informação e Suporte à Decisão | J372: Sistêmico | K372: Sim
A373: =_xlfn.XLOOKUP(B373,' Lista de Entrevistas'!B:B,' Lista de Entrevistas'!A:A,"") -> 54 | B373: Alexandro Marcelo Zopolato Francisco | C373: Gerência Executiva | D373: Rodovias | E373: “A gente está avançando para padronizar… mas não está pronto.” | F373: Padronização ainda incompleta | G373: Metodologia de gestão CAPEX | H373: Metodologias e Engenharia de Valor | I373: Eficiência Operacional da Execução | J373: Sistêmico | K373: Sim
A374: =_xlfn.XLOOKUP(B374,' Lista de Entrevistas'!B:B,' Lista de Entrevistas'!A:A,"") -> 54 | B374: Alexandro Marcelo Zopolato Francisco | C374: Gerência Executiva | D374: Rodovias | E374: “Não temos sistema específico para pleitos.” | F374: Gestão de pleitos não sistematizada | G374: Pleitos e aditivos | H374: Gestão Contratual e Contingências | I374: Exposição a Riscos de Investimento | J374: Multi-Projeto | K374: Sim
A375: =_xlfn.XLOOKUP(B375,' Lista de Entrevistas'!B:B,' Lista de Entrevistas'!A:A,"") -> 54 | B375: Alexandro Marcelo Zopolato Francisco | C375: Gerência Executiva | D375: Rodovias | E375: “Cada um exerce sua forma… não existe padrão.” | F375: Execução varia conforme responsável | G375: Governança de portfólio | H375: Gestão de Portfólio e PMO | I375: Confiabilidade da Informação e Suporte à Decisão | J375: Sistêmico | K375: Sim
A376: =_xlfn.XLOOKUP(B376,' Lista de Entrevistas'!B:B,' Lista de Entrevistas'!A:A,"") -> 54 | B376: Alexandro Marcelo Zopolato Francisco | C376: Gerência Executiva | D376: Rodovias | E376: “O sistema matricial… garante governança, mas perde velocidade.” | F376: Trade-off estrutural entre governança e agilidade | G376: Modelo organizacional | H376: Estrutura Organizacional e Governança do CAPEX | I376: Previsibilidade de Prazo e Entrega | J376: Sistêmico | K376: Sim
A377: =_xlfn.XLOOKUP(B377,' Lista de Entrevistas'!B:B,' Lista de Entrevistas'!A:A,"") -> 54 | B377: Alexandro Marcelo Zopolato Francisco | C377: Gerência Executiva | D377: Rodovias | E377: “O sistema é feito para travar… não para ser eficiente.” | F377: Processos desenhados para controle e não eficiência | G377: Ritos e Fluxo de Governança | H377: Estrutura Organizacional e Governança do CAPEX | I377: Eficiência Operacional da Execução | J377: Sistêmico | K377: Sim
A378: =_xlfn.XLOOKUP(B378,' Lista de Entrevistas'!B:B,' Lista de Entrevistas'!A:A,"") -> 54 | B378: Alexandro Marcelo Zopolato Francisco | C378: Gerência Executiva | D378: Rodovias | E378: “Um assunto que levaria 1 dia leva 15.” | F378: Tempo de decisão excessivo | G378: Ritos e Fluxo de Governança | H378: Estrutura Organizacional e Governança do CAPEX | I378: Previsibilidade de Prazo e Entrega | J378: Organizacional | K378: Sim
A379: =_xlfn.XLOOKUP(B379,' Lista de Entrevistas'!B:B,' Lista de Entrevistas'!A:A,"") -> 54 | B379: Alexandro Marcelo Zopolato Francisco | C379: Gerência Executiva | D379: Rodovias | E379: “Muita apresentação… cada um quer de um jeito.” | F379: Esforço elevado em reportes customizados | G379: Indicadores e reports executivos | H379: Gestão de Portfólio e PMO | I379: Eficiência Operacional da Execução | J379: Organizacional | K379: Sim
... A387: =_xlfn.XLOOKUP(B387,' Lista de Entrevistas'!B:B,' Lista de Entrevistas'!A:A,"") -> 55 | B387: Jhonnathan Preisner de Souza | C387: Gerência Executiva | D387: Rodovias | E387: “A minha interface com ela é muito baixa assim.” | F387: Baixa interface direta entre área crítica e núcleo | G387: Governança de portfólio | H387: Gestão de Portfólio e PMO | I387: Efetividade da Governança de CAPEX | J387: Organizacional | K387: Sim
A388: =_xlfn.XLOOKUP(B388,' Lista de Entrevistas'!B:B,' Lista de Entrevistas'!A:A,"") -> 56 | B388: Flavio Roberto Dornelas Camara Pimentel
A389: =_xlfn.XLOOKUP(B389,' Lista de Entrevistas'!B:B,' Lista de Entrevistas'!A:A,"") -> 57 | B389: Marcus Vinicius Figur da Rosa | C389: Diretoria | D389: Trilhos | E389: “Não há uma interface muito... com finanças.” | F389: Interface finanças-engenharia é insuficiente | G389: Integração com áreas corporativas | H389: Estrutura Organizacional e Governança do CAPEX | I389: Confiabilidade da Informação e Suporte à Decisão | J389: Organizacional | K389: Sim
A390: =_xlfn.XLOOKUP(B390,' Lista de Entrevistas'!B:B,' Lista de Entrevistas'!A:A,"") -> 57 | B390: Marcus Vinicius Figur da Rosa | C390: Diretoria | D390: Trilhos | E390: “Não há uma interface muito... com finanças.” | F390: Interface finanças-engenharia é insuficiente | G390: Integração com áreas corporativas | H390: Estrutura Organizacional e Governança do CAPEX | I390: Eficiência e Controle de Capital | J390: Organizacional | K390: Sim
A391: =_xlfn.XLOOKUP(B391,' Lista de Entrevistas'!B:B,' Lista de Entrevistas'!A:A,"") -> 57 | B391: Marcus Vinicius Figur da Rosa | C391: Diretoria | D391: Trilhos | E391: “A gente tem que estar muito junto para fazer orçamento, fazer acompanhamento.” | F391: Orçamento e acompanhamento não são integrados | G391: Monitoramento físico-financeiro | H391: Gestão de Portfólio e PMO | I391: Eficiência e Controle de Capital | J391: Organizacional | K391: Sim
A392: =_xlfn.XLOOKUP(B392,' Lista de Entrevistas'!B:B,' Lista de Entrevistas'!A:A,"") -> 57 | B392: Marcus Vinicius Figur da Rosa | C392: Diretoria | D392: Trilhos | E392: “A gente tem que estar muito junto para fazer orçamento, fazer acompanhamento.” | F392: Orçamento e acompanhamento não são integrados | G392: Monitoramento físico-financeiro | H392: Gestão de Portfólio e PMO | I392: Confiabilidade da Informação e Suporte à Decisão | J392: Organizacional | K392: Sim
A393: =_xlfn.XLOOKUP(B393,' Lista de Entrevistas'!B:B,' Lista de Entrevistas'!A:A,"") -> 57 | B393: Marcus Vinicius Figur da Rosa | C393: Diretoria | D393: Trilhos | E393: “O próprio processo de medição e pagamento, as coisas ainda são soltas.” | F393: Processo de medição e pagamento é desestruturado | G393: Administração contratual | H393: Gestão Contratual e Contingências | I393: Eficiência Operacional da Execução | J393: Multi-Projeto | K393: Sim
A394: =_xlfn.XLOOKUP(B394,' Lista de Entrevistas'!B:B,' Lista de Entrevistas'!A:A,"") -> 57 | B394: Marcus Vinicius Figur da Rosa | C394: Diretoria | D394: Trilhos | E394: “O próprio processo de medição e pagamento, as coisas ainda são soltas.” | F394: Processo de medição e pagamento é desestruturado | G394: Administração contratual | H394: Gestão Contratual e Contingências | I394: Eficiência e Controle de Capital | J394: Multi-Projeto | K394: Sim
A395: =_xlfn.XLOOKUP(B395,' Lista de Entrevistas'!B:B,' Lista de Entrevistas'!A:A,"") -> 57 | B395: Marcus Vinicius Figur da Rosa | C395: Diretoria | D395: Trilhos | E395: “Muita coisa, a engenharia... traz uma informação muito fechada. Ela não abre.” | F395: Informação de engenharia é pouco transparente | G395: Rastreabilidade da informação | H395: Tecnologia, Dados e Sistemas | I395: Confiabilidade da Informação e Suporte à Decisão | J395: Organizacional | K395: Sim
A396: =_xlfn.XLOOKUP(B396,' Lista de Entrevistas'!B:B,' Lista de Entrevistas'!A:A,"") -> 57 | B396: Marcus Vinicius Figur da Rosa | C396: Diretoria | D396: Trilhos | E396: “Muita coisa, a engenharia... traz uma informação muito fechada. Ela não abre.” | F396: Informação de engenharia é pouco transparente | G396: Rastreabilidade da informação | H396: Tecnologia, Dados e Sistemas | I396: Qualidade da Tomada de Decisão de Investimentos | J396: Organizacional | K396: Sim
A397: =_xlfn.XLOOKUP(B397,' Lista de Entrevistas'!B:B,' Lista de Entrevistas'!A:A,"") -> 57 | B397: Marcus Vinicius Figur da Rosa | C397: Diretoria | D397: Trilhos | E397: “Eu deveria ter... um Masterplan do Capex.” | F397: Ausência de masterplan consolidado de CAPEX | G397: Governança de portfólio | H397: Gestão de Portfólio e PMO | I397: Qualidade da Tomada de Decisão de Investimentos | J397: Sistêmico | K397: Sim
A398: =_xlfn.XLOOKUP(B398,' Lista de Entrevistas'!B:B,' Lista de Entrevistas'!A:A,"") -> 57 | B398: Marcus Vinicius Figur da Rosa | C398: Diretoria | D398: Trilhos | E398: “Eu deveria ter... um Masterplan do Capex.” | F398: Ausência de masterplan consolidado de CAPEX | G398: Governança de portfólio | H398: Gestão de Portfólio e PMO | I398: Previsibilidade de Prazo e Entrega | J398: Sistêmico | K398: Sim
A399: =_xlfn.XLOOKUP(B399,' Lista de Entrevistas'!B:B,' Lista de Entrevistas'!A:A,"") -> 57 | B399: Marcus Vinicius Figur da Rosa | C399: Diretoria | D399: Trilhos | E399: “Tem problemas de caixa.” | F399: Planejamento de desembolso é insuficiente | G399: Monitoramento físico-financeiro | H399: Gestão de Portfólio e PMO | I399: Eficiência e Controle de Capital | J399: Organizacional | K399: Sim
A400: =_xlfn.XLOOKUP(B400,' Lista de Entrevistas'!B:B,' Lista de Entrevistas'!A:A,"") -> 57 | B400: Marcus Vinicius Figur da Rosa | C400: Diretoria | D400: Trilhos | E400: “Talvez o nosso time aqui... precise de um financeiro forte para trocar com eles.” | F400: Capacidade financeira dedicada à implantação é insuficiente | G400: Capacidade e competências | H400: Estrutura Organizacional e Governança do CAPEX | I400: Eficiência Operacional da Execução | J400: Organizacional | K400: Não
... A404: =_xlfn.XLOOKUP(B404,' Lista de Entrevistas'!B:B,' Lista de Entrevistas'!A:A,"") -> 57 | B404: Marcus Vinicius Figur da Rosa | C404: Diretoria | D404: Trilhos | E404: “Como é que a gente acompanha essa execução... a gente está tendo que entrar no micro.” | F404: Controle executivo exige atuação excessivamente micro | G404: Monitoramento físico-financeiro | H404: Gestão de Portfólio e PMO | I404: Eficiência Operacional da Execução | J404: Multi-Projeto | K404: Sim
A405: =_xlfn.XLOOKUP(B405,' Lista de Entrevistas'!B:B,' Lista de Entrevistas'!A:A,"") -> 58 | B405: Alexandre David Magno
A406: =_xlfn.XLOOKUP(B406,' Lista de Entrevistas'!B:B,' Lista de Entrevistas'!A:A,"") -> 59 | B406: João Pita | C406: Diretoria | D406: Trilhos | E406: “Eu participo sim do pré-bid, mas... de uma forma lateral.” | F406: Interface comercial entra lateralmente no pré-bid | G406: Integração pré-bid e originação de projetos | H406: Gestão de Portfólio e PMO | I406: Qualidade da Tomada de Decisão de Investimentos | J406: Organizacional | K406: Sim
A407: =_xlfn.XLOOKUP(B407,' Lista de Entrevistas'!B:B,' Lista de Entrevistas'!A:A,"") -> 59 | B407: João Pita | C407: Diretoria | D407: Trilhos | E407: “Eu vou dando os insumos... mas não sou responsável pelo pré-BID de um leilão.” | F407: Contribuições de valor não estão ancoradas em responsabilidade formal | G407: Papéis e responsabilidades | H407: Estrutura Organizacional e Governança do CAPEX | I407: Efetividade da Governança de CAPEX | J407: Organizacional | K407: Não
A408: =_xlfn.XLOOKUP(B408,' Lista de Entrevistas'!B:B,' Lista de Entrevistas'!A:A,"") -> 59 | B408: João Pita | C408: Diretoria | D408: Trilhos | E408: “A minha única nota é tratar igual o que é igual e diferente do que é diferente.” | F408: Governança não diferencia investimentos por porte | G408: Critérios de avaliação e priorização técnica | H408: Metodologias e Engenharia de Valor | I408: Qualidade da Tomada de Decisão de Investimentos | J408: Sistêmico | K408: Sim
A409: =_xlfn.XLOOKUP(B409,' Lista de Entrevistas'!B:B,' Lista de Entrevistas'!A:A,"") -> 59 | B409: João Pita | C409: Diretoria | D409: Trilhos | E409: “O fluxo não pode ser o mesmo... queria fazer uma rodovia inteira, custa 5 bilhões de reais.” | F409: Fluxos de aprovação não são segmentados por complexidade | G409: Alçadas e decisões | H409: Estrutura Organizacional e Governança do CAPEX | I409: Eficiência Operacional da Execução | J409: Sistêmico | K409: Sim
A410: =_xlfn.XLOOKUP(B410,' Lista de Entrevistas'!B:B,' Lista de Entrevistas'!A:A,"") -> 59 | B410: João Pita | C410: Diretoria | D410: Trilhos | E410: “A gente tem que ser muito mais ágil nas pequenas obras, nas pequenas criações de valor.” | F410: Pequenos investimentos seguem rito excessivamente pesado | G410: Alçadas e decisões | H410: Estrutura Organizacional e Governança do CAPEX | I410: Eficiência Operacional da Execução | J410: Sistêmico | K410: Sim
A411: =_xlfn.XLOOKUP(B411,' Lista de Entrevistas'!B:B,' Lista de Entrevistas'!A:A,"") -> 59 | B411: João Pita | C411: Diretoria | D411: Trilhos | E411: “Hoje é um dos problemas da Motiva em tudo é. Como ela é engessada?” | F411: Governança corporativa é excessivamente engessada | G411: Ritos e Fluxo de Governança | H411: Estrutura Organizacional e Governança do CAPEX | I411: Efetividade da Governança de CAPEX | J411: Sistêmico | K411: Sim
A412: =_xlfn.XLOOKUP(B412,' Lista de Entrevistas'!B:B,' Lista de Entrevistas'!A:A,"") -> 59 | B412: João Pita | C412: Diretoria | D412: Trilhos | E412: “Alguns cenários são um pouco mais caros de capex... com talvez uma contrapartida maior de receita.” | F412: Avaliação de CAPEX não integra cenários de receita | G412: Critérios de avaliação e priorização técnica | H412: Metodologias e Engenharia de Valor | I412: Qualidade da Tomada de Decisão de Investimentos | J412: Multi-Projeto | K412: Não
A413: =_xlfn.XLOOKUP(B413,' Lista de Entrevistas'!B:B,' Lista de Entrevistas'!A:A,"") -> 59 | B413: João Pita | C413: Diretoria | D413: Trilhos | E413: “Eu posso ter um vidro... muito melhor do ponto de vista de capex... mas que ele vai-me dar um opex brutal.” | F413: Decisão de investimento não considera custo total | G413: Engenharia de valor | H413: Metodologias e Engenharia de Valor | I413: Eficiência e Controle de Capital | J413: Multi-Projeto | K413: Sim
A414: =_xlfn.XLOOKUP(B414,' Lista de Entrevistas'!B:B,' Lista de Entrevistas'!A:A,"") -> 59 | B414: João Pita | C414: Diretoria | D414: Trilhos | E414: “O capex por si só não é o fim último.” | F414: Decisão de investimento desconsidera visão de ciclo de vida | G414: Engenharia de valor | H414: Metodologias e Engenharia de Valor | I414: Qualidade da Tomada de Decisão de Investimentos | J414: Multi-Projeto | K414: Sim
A415: =_xlfn.XLOOKUP(B415,' Lista de Entrevistas'!B:B,' Lista de Entrevistas'!A:A,"") -> 60 | B415: Pedro Paulo Archer Sutter
A416: =_xlfn.XLOOKUP(B416,' Lista de Entrevistas'!B:B,' Lista de Entrevistas'!A:A,"") -> 60 | B416: Pedro Paulo Archer Sutter | C416: Executivo (VP) | D416: Corporativo | E416: “Eu não tenho estabelecido ainda essa governança… as iniciativas estão dispersas e cada um partindo para o seu lado.” | F416: Iniciativas estratégicas descentralizadas e sem governança integrada | G416: Governança de portfólio | H416: Gestão de Portfólio e PMO | I416: Efetividade da Governança de CAPEX | J416: Sistêmico | K416: Sim
A417: =_xlfn.XLOOKUP(B417,' Lista de Entrevistas'!B:B,' Lista de Entrevistas'!A:A,"") -> 60 | B417: Pedro Paulo Archer Sutter | C417: Executivo (VP) | D417: Corporativo | E417: “Se o Miguel chegar… quanto a gente investe em inovação… eu não sei.” | F417: Ausência de visibilidade consolidada de investimentos | G417: Monitoramento físico-financeiro | H417: Gestão de Portfólio e PMO | I417: Confiabilidade da Informação e Suporte à Decisão | J417: Sistêmico | K417: Sim
A418: =_xlfn.XLOOKUP(B418,' Lista de Entrevistas'!B:B,' Lista de Entrevistas'!A:A,"") -> 60 | B418: Pedro Paulo Archer Sutter | C418: Executivo (VP) | D418: Corporativo | E418: “Nem o que está no Aevo tem número direito.” | F418: Ferramentas não suportam controle confiável de portfólio | G418: Arquitetura de sistemas | H418: Tecnologia, Dados e Sistemas | I418: Confiabilidade da Informação e Suporte à Decisão | J418: Sistêmico | K418: Sim
A419: =_xlfn.XLOOKUP(B419,' Lista de Entrevistas'!B:B,' Lista de Entrevistas'!A:A,"") -> 60 | B419: Pedro Paulo Archer Sutter | C419: Executivo (VP) | D419: Corporativo | E419: “Os projetos deviam estar lá… eu devia ter um inventário.” | F419: Ausência de inventário único de iniciativas | G419: PMO corporativo e plataformas | H419: Gestão de Portfólio e PMO | I419: Qualidade da Tomada de Decisão de Investimentos | J419: Sistêmico | K419: Sim
A420: =_xlfn.XLOOKUP(B420,' Lista de Entrevistas'!B:B,' Lista de Entrevistas'!A:A,"") -> 60 | B420: Pedro Paulo Archer Sutter | C420: Executivo (VP) | D420: Corporativo | E420: “Cada área está pensando na sua inovação… ninguém vê o conjunto.” | F420: Inovação fragmentada por áreas sem visão sistêmica | G420: Governança técnica e engenharia | H420: Metodologias e Engenharia de Valor | I420: Eficiência Operacional da Execução | J420: Sistêmico | K420: Sim
A421: =_xlfn.XLOOKUP(B421,' Lista de Entrevistas'!B:B,' Lista de Entrevistas'!A:A,"") -> 60 | B421: Pedro Paulo Archer Sutter | C421: Executivo (VP) | D421: Corporativo | E421: “Tem que ter um arquiteto… não existe hoje.” | F421: Falta papel central de orquestração estratégica | G421: Modelo organizacional | H421: Estrutura Organizacional e Governança do CAPEX | I421: Efetividade da Governança de CAPEX | J421: Sistêmico | K421: Sim
A422: =_xlfn.XLOOKUP(B422,' Lista de Entrevistas'!B:B,' Lista de Entrevistas'!A:A,"") -> 60 | B422: Pedro Paulo Archer Sutter | C422: Executivo (VP) | D422: Corporativo | E422: “A inovação não é digital… está misturada e não organizada.” | F422: Falta clareza conceitual e organizacional de inovação | G422: Modelo organizacional | H422: Estrutura Organizacional e Governança do CAPEX | I422: Efetividade da Governança de CAPEX | J422: Organizacional | K422: Sim
A423: =_xlfn.XLOOKUP(B423,' Lista de Entrevistas'!B:B,' Lista de Entrevistas'!A:A,"") -> 60 | B423: Pedro Paulo Archer Sutter | C423: Executivo (VP) | D423: Corporativo | E423: “Tem muita coisa fora… o que você não mede você não entende.” | F423: Baixa cobertura de dados e rastreabilidade | G423: Modelo e governança de dados | H423: Tecnologia, Dados e Sistemas | I423: Confiabilidade da Informação e Suporte à Decisão | J423: Sistêmico | K423: Sim
A424: =_xlfn.XLOOKUP(B424,' Lista de Entrevistas'!B:B,' Lista de Entrevistas'!A:A,"") -> 60 | B424: Pedro Paulo Archer Sutter | C424: Executivo (VP) | D424: Corporativo | E424: “O maior risco que a gente tem é CAPEX.” | F424: Gestão de CAPEX não estruturada frente à criticidade estratégica | G424: Governança de portfólio | H424: Gestão de Portfólio e PMO | I424: Exposição a Riscos de Investimento | J424: Sistêmico | K424: Sim
A425: =_xlfn.XLOOKUP(B425,' Lista de Entrevistas'!B:B,' Lista de Entrevistas'!A:A,"") -> 60 | B425: Pedro Paulo Archer Sutter | C425: Executivo (VP) | D425: Corporativo | E425: “A empresa hoje é uma grande gestora de CAPEX.” | F425: Modelo operacional depende de excelência em CAPEX não estruturada | G425: Governança de portfólio | H425: Gestão de Portfólio e PMO | I425: Eficiência e Controle de Capital | J425: Sistêmico | K425: Sim
A426: =_xlfn.XLOOKUP(B426,' Lista de Entrevistas'!B:B,' Lista de Entrevistas'!A:A,"") -> 60 | B426: Pedro Paulo Archer Sutter | C426: Executivo (VP) | D426: Corporativo | E426: “O processo decisório precisa ser vivo… hoje ele trava velocidade.” | F426: Governança reduz velocidade de decisão | G426: Ritos e Fluxo de Governança | H426: Estrutura Organizacional e Governança do CAPEX | I426: Previsibilidade de Prazo e Entrega | J426: Organizacional | K426: Sim
A427: =_xlfn.XLOOKUP(B427,' Lista de Entrevistas'!B:B,' Lista de Entrevistas'!A:A,"") -> 60 | B427: Pedro Paulo Archer Sutter | C427: Executivo (VP) | D427: Corporativo | E427: “Temos um legado ainda para limpar… muitos sistemas redundantes.” | F427: Arquitetura de sistemas fragmentada e redundante | G427: Integração entre sistemas | H427: Tecnologia, Dados e Sistemas | I427: Eficiência Operacional da Execução | J427: Sistêmico | K427: Sim
... A430: =_xlfn.XLOOKUP(B430,' Lista de Entrevistas'!B:B,' Lista de Entrevistas'!A:A,"") -> 60 | B430: Pedro Paulo Archer Sutter | C430: Executivo (VP) | D430: Corporativo | E430: “Tudo isso precisa estar conectado… sistemas, BIM, ERP.” | F430: Falta backbone tecnológico integrado | G430: Arquitetura de sistemas | H430: Tecnologia, Dados e Sistemas | I430: Eficiência e Controle de Capital | J430: Sistêmico | K430: Sim
A431: =_xlfn.XLOOKUP(B431,' Lista de Entrevistas'!B:B,' Lista de Entrevistas'!A:A,"") -> 61 | B431: Giancarlo Ferreira
A432: =_xlfn.XLOOKUP(B432,' Lista de Entrevistas'!B:B,' Lista de Entrevistas'!A:A,"") -> 61 | B432: Giancarlo Ferreira | C432: Gerência | D432: Corporativo | E432: “Eu senti muita falta de ter pessoas olhando, pessoas com conhecimento técnico, olhando os nossos estudos de fato.” | F432: Falta capacidade técnica para revisão de estudos econômicos | G432: Capacidade e competências | H432: Estrutura Organizacional e Governança do CAPEX | I432: Qualidade da Tomada de Decisão de Investimentos | J432: Organizacional | K432: Sim
A433: =_xlfn.XLOOKUP(B433,' Lista de Entrevistas'!B:B,' Lista de Entrevistas'!A:A,"") -> 61 | B433: Giancarlo Ferreira | C433: Gerência | D433: Corporativo | E433: “Eu senti muita falta de ter pessoas olhando, pessoas com conhecimento técnico, olhando os nossos estudos de fato.” | F433: Falta capacidade técnica para revisão de estudos econômicos | G433: Capacidade e competências | H433: Estrutura Organizacional e Governança do CAPEX | I433: Eficiência e Controle de Capital | J433: Organizacional | K433: Sim
A434: =_xlfn.XLOOKUP(B434,' Lista de Entrevistas'!B:B,' Lista de Entrevistas'!A:A,"") -> 61 | B434: Giancarlo Ferreira | C434: Gerência | D434: Corporativo | E434: “A gente não tem uma metodologia única na empresa.” | F434: Ausência de metodologia única de apuração financeira | G434: Metodologia de gestão CAPEX | H434: Metodologias e Engenharia de Valor | I434: Confiabilidade da Informação e Suporte à Decisão | J434: Sistêmico | K434: Sim
A435: =_xlfn.XLOOKUP(B435,' Lista de Entrevistas'!B:B,' Lista de Entrevistas'!A:A,"") -> 61 | B435: Giancarlo Ferreira | C435: Gerência | D435: Corporativo | E435: “A gente não tem uma metodologia única na empresa.” | F435: Ausência de metodologia única de apuração financeira | G435: Metodologia de gestão CAPEX | H435: Metodologias e Engenharia de Valor | I435: Qualidade da Tomada de Decisão de Investimentos | J435: Sistêmico | K435: Sim
A436: =_xlfn.XLOOKUP(B436,' Lista de Entrevistas'!B:B,' Lista de Entrevistas'!A:A,"") -> 61 | B436: Giancarlo Ferreira | C436: Gerência | D436: Corporativo | E436: “Rodovias trata de um jeito, trilhos de outro.” | F436: Metodologias divergentes entre plataformas | G436: Padrões e templates | H436: Metodologias e Engenharia de Valor | I436: Confiabilidade da Informação e Suporte à Decisão | J436: Sistêmico | K436: Sim
A437: =_xlfn.XLOOKUP(B437,' Lista de Entrevistas'!B:B,' Lista de Entrevistas'!A:A,"") -> 61 | B437: Giancarlo Ferreira | C437: Gerência | D437: Corporativo | E437: “Rodovias trata de um jeito, trilhos de outro.” | F437: Metodologias divergentes entre plataformas | G437: Padrões e templates | H437: Metodologias e Engenharia de Valor | I437: Efetividade da Governança de CAPEX | J437: Sistêmico | K437: Sim
A438: =_xlfn.XLOOKUP(B438,' Lista de Entrevistas'!B:B,' Lista de Entrevistas'!A:A,"") -> 61 | B438: Giancarlo Ferreira | C438: Gerência | D438: Corporativo | E438: “Cada um tomou a sua decisão de como fazer.” | F438: Decisões metodológicas descentralizadas sem governança | G438: Governança de portfólio | H438: Gestão de Portfólio e PMO | I438: Efetividade da Governança de CAPEX | J438: Sistêmico | K438: Sim
A439: =_xlfn.XLOOKUP(B439,' Lista de Entrevistas'!B:B,' Lista de Entrevistas'!A:A,"") -> 61 | B439: Giancarlo Ferreira | C439: Gerência | D439: Corporativo | E439: “Cada um tomou a sua decisão de como fazer.” | F439: Decisões metodológicas descentralizadas sem governança | G439: Governança de portfólio | H439: Gestão de Portfólio e PMO | I439: Confiabilidade da Informação e Suporte à Decisão | J439: Sistêmico | K439: Sim
A440: =_xlfn.XLOOKUP(B440,' Lista de Entrevistas'!B:B,' Lista de Entrevistas'!A:A,"") -> 61 | B440: Giancarlo Ferreira | C440: Gerência | D440: Corporativo | E440: “As metodologias que eles foram construídas são frágeis.” | F440: Business cases são construídos com metodologia frágil | G440: Critérios de avaliação e priorização técnica | H440: Metodologias e Engenharia de Valor | I440: Qualidade da Tomada de Decisão de Investimentos | J440: Sistêmico | K440: Sim
A441: =_xlfn.XLOOKUP(B441,' Lista de Entrevistas'!B:B,' Lista de Entrevistas'!A:A,"") -> 61 | B441: Giancarlo Ferreira | C441: Gerência | D441: Corporativo | E441: “As metodologias que eles foram construídas são frágeis.” | F441: Business cases são construídos com metodologia frágil | G441: Critérios de avaliação e priorização técnica | H441: Metodologias e Engenharia de Valor | I441: Eficiência e Controle de Capital | J441: Sistêmico | K441: Sim
A442: =_xlfn.XLOOKUP(B442,' Lista de Entrevistas'!B:B,' Lista de Entrevistas'!A:A,"") -> 61 | B442: Giancarlo Ferreira | C442: Gerência | D442: Corporativo | E442: “Projetos que você tem um VPL apontado lá com muita fragilidade.” | F442: Indicadores financeiros de aprovação são pouco robustos | G442: Critérios de avaliação e priorização técnica | H442: Metodologias e Engenharia de Valor | I442: Qualidade da Tomada de Decisão de Investimentos | J442: Organizacional | K442: Sim
A443: =_xlfn.XLOOKUP(B443,' Lista de Entrevistas'!B:B,' Lista de Entrevistas'!A:A,"") -> 61 | B443: Giancarlo Ferreira | C443: Gerência | D443: Corporativo | E443: “Projetos que você tem um VPL apontado lá com muita fragilidade.” | F443: Indicadores financeiros de aprovação são pouco robustos | G443: Critérios de avaliação e priorização técnica | H443: Metodologias e Engenharia de Valor | I443: Exposição a Riscos de Investimento | J443: Organizacional | K443: Sim
... A470: =_xlfn.XLOOKUP(B470,' Lista de Entrevistas'!B:B,' Lista de Entrevistas'!A:A,"") -> 61 | B470: Giancarlo Ferreira | C470: Gerência | D470: Corporativo | E470: “Trilhos vive o mundo deles, rodovias vive o mundo deles e a gente aqui também vive o nosso.” | F470: Plataformas operam como mundos separados | G470: Modelo organizacional | H470: Estrutura Organizacional e Governança do CAPEX | I470: Efetividade da Governança de CAPEX | J470: Sistêmico | K470: Sim
A471: =_xlfn.XLOOKUP(B471,' Lista de Entrevistas'!B:B,' Lista de Entrevistas'!A:A,"") -> 62 | B471: Douglas Pereira de Oliveira Ribeiro
A472: =_xlfn.XLOOKUP(B472,' Lista de Entrevistas'!B:B,' Lista de Entrevistas'!A:A,"") -> 62 | B472: Douglas Pereira de Oliveira Ribeiro | C472: Gerência | D472: Corporativo | E472: “Não temos centralização de informação nem padronização.” | F472: Dados de CAPEX descentralizados e não padronizados | G472: Modelo e governança de dados | H472: Tecnologia, Dados e Sistemas | I472: Confiabilidade da Informação e Suporte à Decisão | J472: Sistêmico | K472: Sim
A473: =_xlfn.XLOOKUP(B473,' Lista de Entrevistas'!B:B,' Lista de Entrevistas'!A:A,"") -> 62 | B473: Douglas Pereira de Oliveira Ribeiro | C473: Gerência | D473: Corporativo | E473: “Recebemos informação muito técnica ou em granularidade inadequada.” | F473: Informação não adequada ao público consumidor | G473: Indicadores e reports executivos | H473: Gestão de Portfólio e PMO | I473: Qualidade da Tomada de Decisão de Investimentos | J473: Organizacional | K473: Sim
A474: =_xlfn.XLOOKUP(B474,' Lista de Entrevistas'!B:B,' Lista de Entrevistas'!A:A,"") -> 62 | B474: Douglas Pereira de Oliveira Ribeiro | C474: Gerência | D474: Corporativo | E474: “Cada um responde de um jeito, não existe padrão.” | F474: Ausência de padronização na geração de informações | G474: Padrões e templates | H474: Metodologias e Engenharia de Valor | I474: Confiabilidade da Informação e Suporte à Decisão | J474: Sistêmico | K474: Sim
A475: =_xlfn.XLOOKUP(B475,' Lista de Entrevistas'!B:B,' Lista de Entrevistas'!A:A,"") -> 62 | B475: Douglas Pereira de Oliveira Ribeiro | C475: Gerência | D475: Corporativo | E475: “A gente perde muito tempo para chegar na informação final.” | F475: Baixa eficiência na consolidação de informações | G475: Planejamento integrado | H475: Planejamento Integrado | I475: Eficiência Operacional da Execução | J475: Organizacional | K475: Sim
A476: =_xlfn.XLOOKUP(B476,' Lista de Entrevistas'!B:B,' Lista de Entrevistas'!A:A,"") -> 62 | B476: Douglas Pereira de Oliveira Ribeiro | C476: Gerência | D476: Corporativo | E476: “Temos dificuldade de base de dados e estruturação.” | F476: Falta de estruturação e rastreabilidade dos dados | G476: Modelo e governança de dados | H476: Tecnologia, Dados e Sistemas | I476: Confiabilidade da Informação e Suporte à Decisão | J476: Sistêmico | K476: Sim
A477: =_xlfn.XLOOKUP(B477,' Lista de Entrevistas'!B:B,' Lista de Entrevistas'!A:A,"") -> 62 | B477: Douglas Pereira de Oliveira Ribeiro | C477: Gerência | D477: Corporativo | E477: “Não conseguimos acompanhar o número do bid ao longo do tempo.” | F477: Ausência de tracking estruturado do CAPEX vs BID | G477: Monitoramento físico-financeiro | H477: Gestão de Portfólio e PMO | I477: Qualidade da Tomada de Decisão de Investimentos | J477: Sistêmico | K477: Sim
A478: =_xlfn.XLOOKUP(B478,' Lista de Entrevistas'!B:B,' Lista de Entrevistas'!A:A,"") -> 62 | B478: Douglas Pereira de Oliveira Ribeiro | C478: Gerência | D478: Corporativo | E478: “A informação não está centralizada, eles precisam buscar.” | F478: Dependência de coleta manual de informações | G478: Tecnologia e dados | H478: Tecnologia, Dados e Sistemas | I478: Eficiência Operacional da Execução | J478: Sistêmico | K478: Sim
A479: =_xlfn.XLOOKUP(B479,' Lista de Entrevistas'!B:B,' Lista de Entrevistas'!A:A,"") -> 62 | B479: Douglas Pereira de Oliveira Ribeiro | C479: Gerência | D479: Corporativo | E479: “Processo é muito sensível e já teve erro recorrente.” | F479: Fragilidade na governança e validação de dados críticos | G479: Governança de dados | H479: Tecnologia, Dados e Sistemas | I479: Exposição a Riscos de Investimento | J479: Sistêmico | K479: Sim
A480: =_xlfn.XLOOKUP(B480,' Lista de Entrevistas'!B:B,' Lista de Entrevistas'!A:A,"") -> 62 | B480: Douglas Pereira de Oliveira Ribeiro | C480: Gerência | D480: Corporativo | E480: “Não temos análise sistemática de desvios.” | F480: Falta de análise estruturada de desvios CAPEX | G480: Monitoramento físico-financeiro | H480: Gestão de Portfólio e PMO | I480: Qualidade da Tomada de Decisão de Investimentos | J480: Sistêmico | K480: Sim
A481: =_xlfn.XLOOKUP(B481,' Lista de Entrevistas'!B:B,' Lista de Entrevistas'!A:A,"") -> 62 | B481: Douglas Pereira de Oliveira Ribeiro | C481: Gerência | D481: Corporativo | E481: “A interação com o núcleo é sob demanda, não periódica.” | F481: Ausência de rotina estruturada de governança com stakeholders | G481: Comitês e fóruns | H481: Estrutura Organizacional e Governança do CAPEX | I481: Efetividade da Governança de CAPEX | J481: Organizacional | K481: Sim
A482: =_xlfn.XLOOKUP(B482,' Lista de Entrevistas'!B:B,' Lista de Entrevistas'!A:A,"") -> 62 | B482: Douglas Pereira de Oliveira Ribeiro | C482: Gerência | D482: Corporativo | E482: “Não existe procedimento formal dessas interações.” | F482: Governança não formalizada nas interfaces críticas | G482: Ritos e Fluxo de Governança | H482: Estrutura Organizacional e Governança do CAPEX | I482: Efetividade da Governança de CAPEX | J482: Organizacional | K482: Sim
A483: =_xlfn.XLOOKUP(B483,' Lista de Entrevistas'!B:B,' Lista de Entrevistas'!A:A,"") -> 63 | B483: Camila Gil Henriques Marinheiro
A484: =_xlfn.XLOOKUP(B484,' Lista de Entrevistas'!B:B,' Lista de Entrevistas'!A:A,"") -> 63 | B484: Camila Gil Henriques Marinheiro | C484: Gerência | D484: Corporativo | E484: “Cada uma fazia uma reunião de status dos seus projetos com formatos totalmente diferentes.” | F484: Ausência de padronização de ritos e reports de projetos | G484: Ritos e Fluxo de Governança | H484: Estrutura Organizacional e Governança do CAPEX | I484: Confiabilidade da Informação e Suporte à Decisão | J484: Organizacional | K484: Sim
A485: =_xlfn.XLOOKUP(B485,' Lista de Entrevistas'!B:B,' Lista de Entrevistas'!A:A,"") -> 63 | B485: Camila Gil Henriques Marinheiro | C485: Gerência | D485: Corporativo | E485: “A entrada das demandas… cada um fazia do seu jeito.” | F485: Entrada de demandas não padronizada entre áreas | G485: Governança de portfólio | H485: Gestão de Portfólio e PMO | I485: Eficiência Operacional da Execução | J485: Organizacional | K485: Sim
A486: =_xlfn.XLOOKUP(B486,' Lista de Entrevistas'!B:B,' Lista de Entrevistas'!A:A,"") -> 63 | B486: Camila Gil Henriques Marinheiro | C486: Gerência | D486: Corporativo | E486: “Nunca tive atuação com o núcleo para entender dores ou fomentar projetos.” | F486: Atuação reativa sem gestão estruturada de demanda | G486: Governança de portfólio | H486: Gestão de Portfólio e PMO | I486: Efetividade da Governança de CAPEX | J486: Organizacional | K486: Sim
A487: =_xlfn.XLOOKUP(B487,' Lista de Entrevistas'!B:B,' Lista de Entrevistas'!A:A,"") -> 63 | B487: Camila Gil Henriques Marinheiro | C487: Gerência | D487: Corporativo | E487: “Estou mais apagando fogo… atuando de forma reativa.” | F487: Modelo operacional reativo na gestão de demandas | G487: Cultura e modelo organizacional | H487: Estrutura Organizacional e Governança do CAPEX | I487: Eficiência Operacional da Execução | J487: Organizacional | K487: Sim
A488: =_xlfn.XLOOKUP(B488,' Lista de Entrevistas'!B:B,' Lista de Entrevistas'!A:A,"") -> 63 | B488: Camila Gil Henriques Marinheiro | C488: Gerência | D488: Corporativo | E488: “A arquitetura ainda não está clara… quais sistemas vão ficar.” | F488: Arquitetura de sistemas indefinida para o modelo futuro | G488: Arquitetura de sistemas | H488: Tecnologia, Dados e Sistemas | I488: Confiabilidade da Informação e Suporte à Decisão | J488: Sistêmico | K488: Sim
A489: =_xlfn.XLOOKUP(B489,' Lista de Entrevistas'!B:B,' Lista de Entrevistas'!A:A,"") -> 63 | B489: Camila Gil Henriques Marinheiro | C489: Gerência | D489: Corporativo | E489: “Migração de dados de projetos em andamento é uma preocupação grande.” | F489: Risco elevado na migração de dados de CAPEX | G489: Modelo e governança de dados | H489: Tecnologia, Dados e Sistemas | I489: Exposição a Riscos de Investimento | J489: Sistêmico | K489: Sim
A490: =_xlfn.XLOOKUP(B490,' Lista de Entrevistas'!B:B,' Lista de Entrevistas'!A:A,"") -> 63 | B490: Camila Gil Henriques Marinheiro | C490: Gerência | D490: Corporativo | E490: “Cada ponto focal vai defender o seu processo atual.” | F490: Ausência de processo to-be consolidado e alinhado | G490: Metodologia de gestão CAPEX | H490: Metodologias e Engenharia de Valor | I490: Efetividade da Governança de CAPEX | J490: Sistêmico | K490: Sim
...

Sheet Impactos x Entrevistas
A1: impacto | B1: ocorrencias | C1: entrevistas_afetadas
A2: Previsibilidade de Prazo e Entrega | B2: =COUNTIF('Analise Individual (2)'!$I$2:$I$974,A2) -> 46
A3: Eficiência e Controle de Capital | B3: =COUNTIF('Analise Individual (2)'!$I$2:$I$974,A3) -> 32
A4: Qualidade da Tomada de Decisão de Investimentos | B4: =COUNTIF('Analise Individual (2)'!$I$2:$I$974,A4) -> 69
A5: Efetividade da Governança de CAPEX | B5: =COUNTIF('Analise Individual (2)'!$I$2:$I$974,A5) -> 100
A6: Eficiência Operacional da Execução | B6: =COUNTIF('Analise Individual (2)'!$I$2:$I$974,A6) -> 135
A7: Exposição a Riscos de Investimento | B7: =COUNTIF('Analise Individual (2)'!$I$2:$I$974,A7) -> 42
A8: Qualidade Técnica e Maturidade de Engenharia | B8: =COUNTIF('Analise Individual (2)'!$I$2:$I$974,A8) -> 8
A9: Performance Contratual e Cadeia de Fornecimento | B9: =COUNTIF('Analise Individual (2)'!$I$2:$I$974,A9) -> 39
A10: Confiabilidade da Informação e Suporte à Decisão | B10: =COUNTIF('Analise Individual (2)'!$I$2:$I$974,A10) -> 108

Sheet Consolidacao Geral (2)
A1: problema_estrutural | B1: disciplina | C1: dimensao | D1: ocorrencias
A2: Integração sistêmica insuficiente entre ferramentas de CAPEX | B2: Integração entre sistemas | C2: Tecnologia, Dados e Sistemas | D2: 6
A3: Padronização insuficiente entre plataformas de CAPEX | B3: Metodologia de gestão CAPEX | C3: Metodologias e Engenharia de Valor | D3: 4
A4: Alçadas de decisão insuficientes na implantação | B4: Alçadas e decisões | C4: Estrutura Organizacional e Governança | D4: 3
A5: Capacidade insuficiente para planejamento avançado | B5: Capacidade e competências | C5: Estrutura Organizacional e Governança | D5: 3
A6: Consolidação manual de informações físico-financeiras | B6: Monitoramento físico-financeiro | C6: Gestão de Portfólio e PMO | D6: 3
A7: Gestão contratual e riscos pulverizada entre áreas | B7: Modelo organizacional | C7: Estrutura Organizacional e Governança | D7: 3
A8: Papéis e responsabilidades ainda indefinidos pós-reestruturação | B8: Papéis e responsabilidades | C8: Estrutura Organizacional e Governança | D8: 3
A9: Baixa concorrência em fornecedores críticos de sistemas | B9: Administração contratual | C9: Gestão Contratual e Contingências | D9: 2
A10: Baixa maturidade de gestão de riscos na ponta | B10: Gestão de Riscos do portfólio | C10: Gestão de Portfólio e PMO | D10: 2
A11: Barreiras matriciais retardam o fluxo de informações | B11: Ritos e Fluxo de Governança | C11: Estrutura Organizacional e Governança | D11: 2
A12: Capacidade insuficiente de PMO frente ao portfólio | B12: PMO corporativo e plataformas | C12: Gestão de Portfólio e PMO | D12: 2
A13: Comunicação contratual sem padronização nem controle | B13: Administração contratual | C13: Gestão Contratual e Contingências | D13: 2
... A52: Visibilidade insuficiente sobre carteiras das demais áreas | B52: Governança de portfólio | C52: Gestão de Portfólio e PMO | D52: 1

Sheet Matriz_Problema_Impacto
A1: problema_estrutural | B1: Previsibilidade de Prazo e Entrega | C1: Eficiência e Controle de Capital | D1: Qualidade da Tomada de Decisão de Investimentos | E1: Efetividade da Governança de CAPEX | F1: Eficiência Operacional da Execução | G1: Exposição a Riscos de Investimento | H1: Qualidade Técnica e Maturidade de Engenharia | I1: Performance Contratual e Cadeia de Fornecimento | J1: Confiabilidade da Informação e Suporte à Decisão | K1: total
A2: Integração sistêmica insuficiente entre ferramentas de CAPEX | B2: 0 | C2: 0 | D2: 0 | E2: 0 | F2: 6 | G2: 0 | H2: 0 | I2: 0 | J2: 6 | K2: 12
A3: Padronização insuficiente entre plataformas de CAPEX | B3: 0 | C3: 0 | D3: 1 | E3: 4 | F3: 3 | G3: 0 | H3: 0 | I3: 0 | J3: 0 | K3: 8
A4: Alçadas de decisão insuficientes na implantação | B4: 2 | C4: 0 | D4: 0 | E4: 2 | F4: 2 | G4: 0 | H4: 0 | I4: 0 | J4: 0 | K4: 6
A5: Capacidade insuficiente para planejamento avançado | B5: 1 | C5: 1 | D5: 0 | E5: 0 | F5: 1 | G5: 0 | H5: 3 | I5: 0 | J5: 0 | K5: 6
A6: Consolidação manual de informações físico-financeiras | B6: 0 | C6: 0 | D6: 0 | E6: 0 | F6: 3 | G6: 0 | H6: 0 | I6: 0 | J6: 3 | K6: 6
A7: Gestão contratual e riscos pulverizada entre áreas | B7: 0 | C7: 0 | D7: 0 | E7: 3 | F7: 0 | G7: 1 | H7: 0 | I7: 2 | J7: 0 | K7: 6
A8: Papéis e responsabilidades ainda indefinidos pós-reestruturação | B8: 0 | C8: 0 | D8: 0 | E8: 3 | F8: 1 | G8: 0 | H8: 0 | I8: 1 | J8: 0 | K8: 5
A9: Baixa concorrência em fornecedores críticos de sistemas | B9: 0 | C9: 0 | D9: 0 | E9: 0 | F9: 0 | G9: 2 | H9: 0 | I9: 2 | J9: 0 | K9: 4
A10: Baixa maturidade de gestão de riscos na ponta | B10: 0 | C10: 0 | D10: 1 | E10: 0 | F10: 0 | G10: 2 | H10: 0 | I10: 0 | J10: 1 | K10: 4
A11: Barreiras matriciais retardam o fluxo de informações | B11: 0 | C11: 0 | D11: 0 | E11: 2 | F11: 0 | G11: 0 | H11: 0 | I11: 0 | J11: 2 | K11: 4
A12: Capacidade insuficiente de PMO frente ao portfólio | B12: 0 | C12: 0 | D12: 0 | E12: 0 | F12: 2 | G12: 0 | H12: 0 | I12: 0 | J12: 2 | K12: 4
A13: Comunicação contratual sem padronização nem controle | B13: 0 | C13: 0 | D13: 0 | E13: 0 | F13: 0 | G13: 0 | H13: 0 | I13: 2 | J13: 2 | K13: 4
... A52: Visibilidade insuficiente sobre carteiras das demais áreas | B52: 0 | C52: 0 | D52: 1 | E52: 0 | F52: 0 | G52: 0 | H52: 0 | I52: 0 | J52: 1 | K52: 2

Sheet Matriz_Dimensao_Impacto
A1: dimensao | B1: Previsibilidade de Prazo e Entrega | C1: Eficiência e Controle de Capital | D1: Qualidade da Tomada de Decisão de Investimentos | E1: Efetividade da Governança de CAPEX | F1: Eficiência Operacional da Execução | G1: Exposição a Riscos de Investimento | H1: Qualidade Técnica e Maturidade de Engenharia | I1: Performance Contratual e Cadeia de Fornecimento | J1: Confiabilidade da Informação e Suporte à Decisão | K1: total
A2: Estrutura Organizacional e Governança do CAPEX | B2: =COUNTIFS('Analise Individual (2)'!H:H,tblDimImp[[#This Row],[dimensao]],'Analise Individual (2)'!I:I,tblDimImp[[#Headers],[Previsibilidade de Prazo e Entrega]]) -> 20 | C2: =COUNTIFS('Analise Individual (2)'!H:H,tblDimImp[[#This Row],[dimensao]],'Analise Individual (2)'!I:I,tblDimImp[[#Headers],[Eficiência e Controle de Capital]]) -> 3 | D2: =COUNTIFS('Analise Individual (2)'!H:H,tblDimImp[[#This Row],[dimensao]],'Analise Individual (2)'!I:I,tblDimImp[[#Headers],[Qualidade da Tomada de Decisão de Investimentos]]) -> 11 | E2: =COUNTIFS('Analise Individual (2)'!H:H,tblDimImp[[#This Row],[dimensao]],'Analise Individual (2)'!I:I,tblDimImp[[#Headers],[Efetividade da Governança de CAPEX]]) -> 66 | F2: =COUNTIFS('Analise Individual (2)'!H:H,tblDimImp[[#This Row],[dimensao]],'Analise Individual (2)'!I:I,tblDimImp[[#Headers],[Eficiência Operacional da Execução]]) -> 45 | G2: =COUNTIFS('Analise Individual (2)'!H:H,tblDimImp[[#This Row],[dimensao]],'Analise Individual (2)'!I:I,tblDimImp[[#Headers],[Exposição a Riscos de Investimento]]) -> 2 | H2: =COUNTIFS('Analise Individual (2)'!H:H,tblDimImp[[#This Row],[dimensao]],'Analise Individual (2)'!I:I,tblDimImp[[#Headers],[Qualidade Técnica e Maturidade de Engenharia]]) -> 4 | I2: =COUNTIFS('Analise Individual (2)'!H:H,tblDimImp[[#This Row],[dimensao]],'Analise Individual (2)'!I:I,tblDimImp[[#Headers],[Performance Contratual e Cadeia de Fornecimento]]) -> 10 | J2: =COUNTIFS('Analise Individual (2)'!H:H,tblDimImp[[#This Row],[dimensao]],'Analise Individual (2)'!I:I,tblDimImp[[#Headers],[Confiabilidade da Informação e Suporte à Decisão]]) -> 8 | K2: =SUM(tblDimImp[[#This Row],[Previsibilidade de Prazo e Entrega]:[Confiabilidade da Informação e Suporte à Decisão]]) -> 169
A3: Metodologias e Engenharia de Valor | B3: =COUNTIFS('Analise Individual (2)'!H:H,tblDimImp[[#This Row],[dimensao]],'Analise Individual (2)'!I:I,tblDimImp[[#Headers],[Previsibilidade de Prazo e Entrega]]) -> 0 | C3: =COUNTIFS('Analise Individual (2)'!H:H,tblDimImp[[#This Row],[dimensao]],'Analise Individual (2)'!I:I,tblDimImp[[#Headers],[Eficiência e Controle de Capital]]) -> 5 | D3: =COUNTIFS('Analise Individual (2)'!H:H,tblDimImp[[#This Row],[dimensao]],'Analise Individual (2)'!I:I,tblDimImp[[#Headers],[Qualidade da Tomada de Decisão de Investimentos]]) -> 21 | E3: =COUNTIFS('Analise Individual (2)'!H:H,tblDimImp[[#This Row],[dimensao]],'Analise Individual (2)'!I:I,tblDimImp[[#Headers],[Efetividade da Governança de CAPEX]]) -> 17 | F3: =COUNTIFS('Analise Individual (2)'!H:H,tblDimImp[[#This Row],[dimensao]],'Analise Individual (2)'!I:I,tblDimImp[[#Headers],[Eficiência Operacional da Execução]]) -> 17 | G3: =COUNTIFS('Analise Individual (2)'!H:H,tblDimImp[[#This Row],[dimensao]],'Analise Individual (2)'!I:I,tblDimImp[[#Headers],[Exposição a Riscos de Investimento]]) -> 1 | H3: =COUNTIFS('Analise Individual (2)'!H:H,tblDimImp[[#This Row],[dimensao]],'Analise Individual (2)'!I:I,tblDimImp[[#Headers],[Qualidade Técnica e Maturidade de Engenharia]]) -> 4 | I3: =COUNTIFS('Analise Individual (2)'!H:H,tblDimImp[[#This Row],[dimensao]],'Analise Individual (2)'!I:I,tblDimImp[[#Headers],[Performance Contratual e Cadeia de Fornecimento]]) -> 2 | J3: =COUNTIFS('Analise Individual (2)'!H:H,tblDimImp[[#This Row],[dimensao]],'Analise Individual (2)'!I:I,tblDimImp[[#Headers],[Confiabilidade da Informação e Suporte à Decisão]]) -> 11 | K3: =SUM(tblDimImp[[#This Row],[Previsibilidade de Prazo e Entrega]:[Confiabilidade da Informação e Suporte à Decisão]]) -> 78
A4: Gestão Contratual e Contingências | B4: =COUNTIFS('Analise Individual (2)'!H:H,tblDimImp[[#This Row],[dimensao]],'Analise Individual (2)'!I:I,tblDimImp[[#Headers],[Previsibilidade de Prazo e Entrega]]) -> 10 | C4: =COUNTIFS('Analise Individual (2)'!H:H,tblDimImp[[#This Row],[dimensao]],'Analise Individual (2)'!I:I,tblDimImp[[#Headers],[Eficiência e Controle de Capital]]) -> 7 | D4: =COUNTIFS('Analise Individual (2)'!H:H,tblDimImp[[#This Row],[dimensao]],'Analise Individual (2)'!I:I,tblDimImp[[#Headers],[Qualidade da Tomada de Decisão de Investimentos]]) -> 0 | E4: =COUNTIFS('Analise Individual (2)'!H:H,tblDimImp[[#This Row],[dimensao]],'Analise Individual (2)'!I:I,tblDimImp[[#Headers],[Efetividade da Governança de CAPEX]]) -> 1 | F4: =COUNTIFS('Analise Individual (2)'!H:H,tblDimImp[[#This Row],[dimensao]],'Analise Individual (2)'!I:I,tblDimImp[[#Headers],[Eficiência Operacional da Execução]]) -> 5 | G4: =COUNTIFS('Analise Individual (2)'!H:H,tblDimImp[[#This Row],[dimensao]],'Analise Individual (2)'!I:I,tblDimImp[[#Headers],[Exposição a Riscos de Investimento]]) -> 20 | H4: =COUNTIFS('Analise Individual (2)'!H:H,tblDimImp[[#This Row],[dimensao]],'Analise Individual (2)'!I:I,tblDimImp[[#Headers],[Qualidade Técnica e Maturidade de Engenharia]]) -> 0 | I4: =COUNTIFS('Analise Individual (2)'!H:H,tblDimImp[[#This Row],[dimensao]],'Analise Individual (2)'!I:I,tblDimImp[[#Headers],[Performance Contratual e Cadeia de Fornecimento]]) -> 26 | J4: =COUNTIFS('Analise Individual (2)'!H:H,tblDimImp[[#This Row],[dimensao]],'Analise Individual (2)'!I:I,tblDimImp[[#Headers],[Confiabilidade da Informação e Suporte à Decisão]]) -> 12 | K4: =SUM(tblDimImp[[#This Row],[Previsibilidade de Prazo e Entrega]:[Confiabilidade da Informação e Suporte à Decisão]]) -> 81
A5: Gestão de Portfólio e PMO | B5: =COUNTIFS('Analise Individual (2)'!H:H,tblDimImp[[#This Row],[dimensao]],'Analise Individual (2)'!I:I,tblDimImp[[#Headers],[Previsibilidade de Prazo e Entrega]]) -> 15 | C5: =COUNTIFS('Analise Individual (2)'!H:H,tblDimImp[[#This Row],[dimensao]],'Analise Individual (2)'!I:I,tblDimImp[[#Headers],[Eficiência e Controle de Capital]]) -> 15 | D5: =COUNTIFS('Analise Individual (2)'!H:H,tblDimImp[[#This Row],[dimensao]],'Analise Individual (2)'!I:I,tblDimImp[[#Headers],[Qualidade da Tomada de Decisão de Investimentos]]) -> 32 | E5: =COUNTIFS('Analise Individual (2)'!H:H,tblDimImp[[#This Row],[dimensao]],'Analise Individual (2)'!I:I,tblDimImp[[#Headers],[Efetividade da Governança de CAPEX]]) -> 15 | F5: =COUNTIFS('Analise Individual (2)'!H:H,tblDimImp[[#This Row],[dimensao]],'Analise Individual (2)'!I:I,tblDimImp[[#Headers],[Eficiência Operacional da Execução]]) -> 30 | G5: =COUNTIFS('Analise Individual (2)'!H:H,tblDimImp[[#This Row],[dimensao]],'Analise Individual (2)'!I:I,tblDimImp[[#Headers],[Exposição a Riscos de Investimento]]) -> 14 | H5: =COUNTIFS('Analise Individual (2)'!H:H,tblDimImp[[#This Row],[dimensao]],'Analise Individual (2)'!I:I,tblDimImp[[#Headers],[Qualidade Técnica e Maturidade de Engenharia]]) -> 0 | I5: =COUNTIFS('Analise Individual (2)'!H:H,tblDimImp[[#This Row],[dimensao]],'Analise Individual (2)'!I:I,tblDimImp[[#Headers],[Performance Contratual e Cadeia de Fornecimento]]) -> 0 | J5: =COUNTIFS('Analise Individual (2)'!H:H,tblDimImp[[#This Row],[dimensao]],'Analise Individual (2)'!I:I,tblDimImp[[#Headers],[Confiabilidade da Informação e Suporte à Decisão]]) -> 29 | K5: =SUM(tblDimImp[[#This Row],[Previsibilidade de Prazo e Entrega]:[Confiabilidade da Informação e Suporte à Decisão]]) -> 150
A6: Tecnologia, Dados e Sistemas | B6: =COUNTIFS('Analise Individual (2)'!H:H,tblDimImp[[#This Row],[dimensao]],'Analise Individual (2)'!I:I,tblDimImp[[#Headers],[Previsibilidade de Prazo e Entrega]]) -> 0 | C6: =COUNTIFS('Analise Individual (2)'!H:H,tblDimImp[[#This Row],[dimensao]],'Analise Individual (2)'!I:I,tblDimImp[[#Headers],[Eficiência e Controle de Capital]]) -> 2 | D6: =COUNTIFS('Analise Individual (2)'!H:H,tblDimImp[[#This Row],[dimensao]],'Analise Individual (2)'!I:I,tblDimImp[[#Headers],[Qualidade da Tomada de Decisão de Investimentos]]) -> 3 | E6: =COUNTIFS('Analise Individual (2)'!H:H,tblDimImp[[#This Row],[dimensao]],'Analise Individual (2)'!I:I,tblDimImp[[#Headers],[Efetividade da Governança de CAPEX]]) -> 0 | F6: =COUNTIFS('Analise Individual (2)'!H:H,tblDimImp[[#This Row],[dimensao]],'Analise Individual (2)'!I:I,tblDimImp[[#Headers],[Eficiência Operacional da Execução]]) -> 34 | G6: =COUNTIFS('Analise Individual (2)'!H:H,tblDimImp[[#This Row],[dimensao]],'Analise Individual (2)'!I:I,tblDimImp[[#Headers],[Exposição a Riscos de Investimento]]) -> 5 | H6: =COUNTIFS('Analise Individual (2)'!H:H,tblDimImp[[#This Row],[dimensao]],'Analise Individual (2)'!I:I,tblDimImp[[#Headers],[Qualidade Técnica e Maturidade de Engenharia]]) -> 0 | I6: =COUNTIFS('Analise Individual (2)'!H:H,tblDimImp[[#This Row],[dimensao]],'Analise Individual (2)'!I:I,tblDimImp[[#Headers],[Performance Contratual e Cadeia de Fornecimento]]) -> 1 | J6: =COUNTIFS('Analise Individual (2)'!H:H,tblDimImp[[#This Row],[dimensao]],'Analise Individual (2)'!I:I,tblDimImp[[#Headers],[Confiabilidade da Informação e Suporte à Decisão]]) -> 48 | K6: =SUM(tblDimImp[[#This Row],[Previsibilidade de Prazo e Entrega]:[Confiabilidade da Informação e Suporte à Decisão]]) -> 93
K7: =SUM(tblDimImp[total]) -> 571

Sheet Hipoteses
A1: hipotese | B1: evidencia_sintese | C1: como_testar | D1: status
A2: A fragmentação entre sistemas e bases impede visão confiável e tempestiva do CAPEX. | B2: Recorrem integração sistêmica insuficiente, consolidação manual e prazos inconsistentes de consolidação. | C2: Mapear fluxos entre SAP, PPM, planilhas e bases locais; medir reconciliações manuais, retrabalho e divergências mensais. | D2: Em construção
A3: O desenho pós-reestruturação ainda não estabilizou papéis, alçadas e handoffs operacionais. | B3: Recorrem papéis indefinidos, alçadas insuficientes, handoffs sem valor e resistência à lógica matricial. | C3: Rastrear decisões críticas por tipo de processo; medir tempos de aprovação, retrabalho e pontos sem dono claro. | D3: Em construção
A4: A maturação insuficiente a montante está elevando aditivos, retrabalho e custo de contratação. | B4: Recorrem engenharia de valor tardia, termos de referência rasos e projetos maturados com baixa antecedência. | C4: Comparar lead time de maturação versus incidência de revisões, pleitos e variações orçamentárias por projeto. | D4: Em construção
A5: O ciclo contratual e de pagamentos opera em ritmo inferior ao necessário para a execução. | B5: Recorrem atrasos de pagamento, morosidade em aditivos, aprovação lenta e fragilidade financeira de fornecedores. | C5: Medir lead time de medição, pagamento e aditivos; cruzar com impacto em mobilização, desempenho e permanência de fornecedores. | D5: Em construção
A6: A gestão de riscos e contingências ainda não fecha o ciclo entre identificação, orçamento e uso efetivo. | B6: Recorrem baixa maturidade de riscos, contingência sem processo integrado e baixa rastreabilidade de utilização. | C6: Auditar fluxo de risco e contingência do registro ao orçamento; comparar previsão, aprovação, uso e reporte. | D6: Em construção
A7: A capacidade crítica de PMO, planejamento e suprimentos está abaixo da complexidade do portfólio. | B7: Recorrem sobrecarga de carteira, falta de pessoas capacitadas, perfis inadequados e conhecimento técnico insuficiente em suprimentos. | C7: Dimensionar carga por função, carteira e especialidade; comparar capacidade instalada, vagas abertas e atrasos associados. | D7: Em construção
A10: Validação final | B10: Geral | C10: Trilhos | D10: Rodovias | E10: Corporativo | F10: Aprofundamento
A11: total_entrevistas_analisadas | B11: =COUNTA(' Lista de Entrevistas'!A2:A85) -> 69 | C11: =COUNTIFS(' Lista de Entrevistas'!$E:$E,Hipoteses!C$10,' Lista de Entrevistas'!$I:$I,"Coleta de Dados") -> 21 | D11: =COUNTIFS(' Lista de Entrevistas'!$E:$E,Hipoteses!D$10,' Lista de Entrevistas'!$I:$I,"Coleta de Dados") -> 18 | E11: =COUNTIFS(' Lista de Entrevistas'!$E:$E,Hipoteses!E$10,' Lista de Entrevistas'!$I:$I,"Coleta de Dados") -> 25 | F11: =B11-C11-D11-E11 -> 5
A12: total_evidencias_validas | B12: {=COUNTA(_xlfn.UNIQUE(_xlfn._xlws.FILTER('Analise Individual (2)'!$E$2:$E$976,'Analise Individual (2)'!$E$2:$E$976<>"")))} -> 406 | C12: {=COUNTA(_xlfn.UNIQUE(_xlfn._xlws.FILTER('Analise Individual (2)'!$E$2:$E$976,'Analise Individual (2)'!$D$2:$D$976=Hipoteses!C$10)))} -> 171 | D12: {=COUNTA(_xlfn.UNIQUE(_xlfn._xlws.FILTER('Analise Individual (2)'!$E$2:$E$976,'Analise Individual (2)'!$D$2:$D$976=Hipoteses!D$10)))} -> 84 | E12: {=COUNTA(_xlfn.UNIQUE(_xlfn._xlws.FILTER('Analise Individual (2)'!$E$2:$E$976,'Analise Individual (2)'!$D$2:$D$976=Hipoteses!E$10)))} -> 151
A13: total_ocorrencias_impacto | B13: =COUNTA('Analise Individual (2)'!$E$2:$E$976) -> 579 | C13: =COUNTIF('Analise Individual (2)'!$D:$D,Hipoteses!C$10) -> 252 | D13: =COUNTIF('Analise Individual (2)'!$D:$D,Hipoteses!D$10) -> 129 | E13: =COUNTIF('Analise Individual (2)'!$D:$D,Hipoteses!E$10) -> 198
A14: total_ocorrencias_recorentes | B14: =COUNTIF('Analise Individual (2)'!K:K,"Sim") -> 477 | C14: =COUNTIFS('Analise Individual (2)'!$K:$K,"Sim",'Analise Individual (2)'!$D:$D,Hipoteses!C$10) -> 178 | D14: =COUNTIFS('Analise Individual (2)'!$K:$K,"Sim",'Analise Individual (2)'!$D:$D,Hipoteses!D$10) -> 110 | E14: =COUNTIFS('Analise Individual (2)'!$K:$K,"Sim",'Analise Individual (2)'!$D:$D,Hipoteses!E$10) -> 189
A15: total_problemas_estruturais_distintos | B15: {=COUNTA(_xlfn.UNIQUE(_xlfn._xlws.FILTER('Analise Individual (2)'!$F$2:$F$976,'Analise Individual (2)'!$F$2:$F$976<>"")))} -> 322 | C15: {=COUNTA(_xlfn.UNIQUE(_xlfn._xlws.FILTER('Analise Individual (2)'!$F$2:$F$976,('Analise Individual (2)'!$F$2:$F$976<>"")*('Analise Individual (2)'!$D$2:$D$976=C10))))} -> 144 | D15: {=COUNTA(_xlfn.UNIQUE(_xlfn._xlws.FILTER('Analise Individual (2)'!$F$2:$F$976,('Analise Individual (2)'!$F$2:$F$976<>"")*('Analise Individual (2)'!$D$2:$D$976=D10))))} -> 65 | E15: {=COUNTA(_xlfn.UNIQUE(_xlfn._xlws.FILTER('Analise Individual (2)'!$F$2:$F$976,('Analise Individual (2)'!$F$2:$F$976<>"")*('Analise Individual (2)'!$D$2:$D$976=E10))))} -> 137
A17: consolidacao | B17: Entrevista da Josiane foi omitida da consolidação

Sheet Consolidacao Geral
A1: Problema Estrutural | B1: Disciplina | C1: Impacto | D1: Abrangência | E1: Nº entrevistas | F1: Recorrente
A2: Coordenação interáreas insuficiente e decisões ad hoc | B2: Organização, Cultura e Modelo Operacional | C2: Governança e Performance do Portfólio | D2: Organizacional | E2: 18 | F2: Sim
A3: Coordenação interáreas insuficiente e decisões ad hoc | B3: Organização, Cultura e Modelo Operacional | C3: Eficiência Operacional | D3: Organizacional | E3: 18 | F3: Sim
A4: Coordenação interáreas insuficiente e decisões ad hoc | B4: Organização, Cultura e Modelo Operacional | C4: Integração Organizacional | D4: Organizacional | E4: 18 | F4: Sim
A5: Fragmentação e baixa integração de sistemas | B5: Tecnologia, Dados e Sistemas | C5: Eficiência Operacional | D5: Organizacional | E5: 9 | F5: Sim
A6: Fragmentação e baixa integração de sistemas | B6: Tecnologia, Dados e Sistemas | C6: Integração Organizacional | D6: Organizacional | E6: 9 | F6: Sim
A7: Fragmentação e baixa integração de sistemas | B7: Tecnologia, Dados e Sistemas | C7: Dados e Sistemas | D7: Organizacional | E7: 9 | F7: Sim
A8: Gestão contratual reativa e com pleitos | B8: Gestão Contratual e Riscos | C8: Prazo e Confiabilidade do Cronograma | D8: Multi-Projeto | E8: 7 | F8: Sim
A9: Gestão contratual reativa e com pleitos | B9: Gestão Contratual e Riscos | C9: Custos e Contingências | D9: Multi-Projeto | E9: 7 | F9: Sim
A10: Gestão contratual reativa e com pleitos | B10: Gestão Contratual e Riscos | C10: Contratos e Cadeia de Fornecimento | D10: Multi-Projeto | E10: 7 | F10: Sim
A11: Governança de custos e contingências insuficiente | B11: Estimativas e Gestão de Custos | C11: Custos e Contingências | D11: Organizacional | E11: 7 | F11: Sim
A12: Governança de custos e contingências insuficiente | B12: Estimativas e Gestão de Custos | C12: Governança e Performance do Portfólio | D12: Organizacional | E12: 7 | F12: Sim
A13: Governança de custos e contingências insuficiente | B13: Estimativas e Gestão de Custos | C13: Riscos e Incertezas | D13: Organizacional | E13: 7 | F13: Sim
... A31: Dados não confiáveis e sem fonte única | B31: Tecnologia, Dados e Sistemas | C31: Dados e Sistemas | D31: Organizacional | E31: 1 | F31: Não

Sheet Matrizes
A1: Matriz Problema Estrutural × Impacto
A2: Problema Estrutural | B2: Prazo e Confiabilidade do Cronograma | C2: Custos e Contingências | D2: Governança e Performance do Portfólio | E2: Eficiência Operacional | F2: Riscos e Incertezas | G2: Integração Organizacional | H2: Maturidade Técnica e Engenharia | I2: Contratos e Cadeia de Fornecimento | J2: Dados e Sistemas
A3: Baixa confiabilidade de planejamento e baseline | B3: 7 | C3: 7 | D3: 7 | E3: 0 | F3: 0 | G3: 0 | H3: 0 | I3: 0 | J3: 0
A4: Contratações sem planejamento e escopo maturado | B4: 3 | C4: 3 | D4: 0 | E4: 0 | F4: 0 | G4: 0 | H4: 0 | I4: 3 | J4: 0
A5: Coordenação interáreas insuficiente e decisões ad hoc | B5: 0 | C5: 0 | D5: 83 | E5: 83 | F5: 0 | G5: 83 | H5: 0 | I5: 0 | J5: 0
A6: Dados não confiáveis e sem fonte única | B6: 0 | C6: 0 | D6: 2 | E6: 2 | F6: 0 | G6: 0 | H6: 0 | I6: 0 | J6: 2
A7: Engenharia de valor tardia e pouco estruturada | B7: 4 | C7: 4 | D7: 4 | E7: 0 | F7: 0 | G7: 0 | H7: 0 | I7: 0 | J7: 0
A8: Fragmentação e baixa integração de sistemas | B8: 0 | C8: 0 | D8: 0 | E8: 12 | F8: 0 | G8: 12 | H8: 0 | I8: 0 | J8: 12
A9: Gestão contratual reativa e com pleitos | B9: 12 | C9: 12 | D9: 0 | E9: 0 | F9: 0 | G9: 0 | H9: 0 | I9: 12 | J9: 0
A10: Governança de custos e contingências insuficiente | B10: 0 | C10: 11 | D10: 11 | E10: 0 | F10: 11 | G10: 0 | H10: 0 | I10: 0 | J10: 0
A11: Papéis e alçadas pouco claros na governança | B11: 0 | C11: 0 | D11: 7 | E11: 7 | F11: 0 | G11: 7 | H11: 0 | I11: 0 | J11: 0
A12: Perda de conhecimento por baixa rastreabilidade | B12: 0 | C12: 0 | D12: 0 | E12: 4 | F12: 0 | G12: 4 | H12: 0 | I12: 0 | J12: 4
A14: Matriz — Categoria de Problema × Impacto
A15: Categoria de Problema | B15: Prazo e Confiabilidade do Cronograma | C15: Custos e Contingências | D15: Governança e Performance do Portfólio | E15: Eficiência Operacional | F15: Riscos e Incertezas | G15: Integração Organizacional | H15: Maturidade Técnica e Engenharia | I15: Contratos e Cadeia de Fornecimento | J15: Dados e Sistemas
A16: Planejamento e baseline | B16: 7 | C16: 7 | D16: 7 | E16: 0 | F16: 0 | G16: 0 | H16: 0 | I16: 3 | J16: 0
A17: Custos e contingências | B17: 0 | C17: 11 | D17: 11 | E17: 0 | F17: 11 | G17: 0 | H17: 0 | I17: 0 | J17: 0
A18: Governança e alçadas | B18: 0 | C18: 0 | D18: 7 | E18: 7 | F18: 0 | G18: 7 | H18: 0 | I18: 0 | J18: 0
A19: Integração e coordenação | B19: 0 | C19: 0 | D19: 83 | E19: 83 | F19: 0 | G19: 83 | H19: 0 | I19: 0 | J19: 0
A20: Gestão contratual | B20: 12 | C20: 12 | D20: 0 | E20: 0 | F20: 0 | G20: 0 | H20: 0 | I20: 12 | J20: 0
A21: Dados e rastreabilidade | B21: 0 | C21: 0 | D21: 2 | E21: 2 | F21: 0 | G21: 0 | H21: 0 | I21: 0 | J21: 2
A22: Engenharia de valor | B22: 4 | C22: 4 | D22: 4 | E22: 0 | F22: 0 | G22: 0 | H22: 0 | I22: 0 | J22: 0
A24: Matriz — Problema Estrutural × Impacto (Nº de entrevistas)
A25: Problema Estrutural | B25: Prazo e Confiabilidade do Cronograma | C25: Custos e Contingências | D25: Governança e Performance do Portfólio | E25: Eficiência Operacional | F25: Riscos e Incertezas | G25: Integração Organizacional | H25: Maturidade Técnica e Engenharia | I25: Contratos e Cadeia de Fornecimento | J25: Dados, Sistemas e Informação
A26: Baixa confiabilidade de planejamento e baseline | B26: 3 | C26: 3 | D26: 3 | E26: 0 | F26: 0 | G26: 0 | H26: 0 | I26: 0 | J26: 0
A27: Contratações sem planejamento e escopo maturado | B27: 3 | C27: 3 | D27: 0 | E27: 0 | F27: 0 | G27: 0 | H27: 0 | I27: 3 | J27: 0
A28: Coordenação interáreas insuficiente e decisões ad hoc | B28: 0 | C28: 0 | D28: 13 | E28: 13 | F28: 0 | G28: 13 | H28: 0 | I28: 0 | J28: 0
A29: Dados não confiáveis e sem fonte única | B29: 0 | C29: 0 | D29: 2 | E29: 2 | F29: 0 | G29: 0 | H29: 0 | I29: 0 | J29: 2
A30: Engenharia de valor tardia e pouco estruturada | B30: 2 | C30: 2 | D30: 2 | E30: 0 | F30: 0 | G30: 0 | H30: 0 | I30: 0 | J30: 0
A31: Fragmentação e baixa integração de sistemas | B31: 0 | C31: 0 | D31: 0 | E31: 3 | F31: 0 | G31: 3 | H31: 0 | I31: 0 | J31: 3
A32: Gestão contratual reativa e com pleitos | B32: 7 | C32: 7 | D32: 0 | E32: 0 | F32: 0 | G32: 0 | H32: 0 | I32: 7 | J32: 0
A33: Governança de custos e contingências insuficiente | B33: 0 | C33: 7 | D33: 7 | E33: 0 | F33: 7 | G33: 0 | H33: 0 | I33: 0 | J33: 0
A34: Papéis e alçadas pouco claros na governança | B34: 0 | C34: 0 | D34: 4 | E34: 4 | F34: 0 | G34: 4 | H34: 0 | I34: 0 | J34: 0
A35: Perda de conhecimento por baixa rastreabilidade | B35: 0 | C35: 0 | D35: 0 | E35: 3 | F35: 0 | G35: 3 | H35: 0 | I35: 0 | J35: 3
A37: Matriz de Diagnóstico — Disciplina × Impacto CAPEX
A38: Disciplina | B38: Prazo e Confiabilidade do Cronograma | C38: Custos e Contingências | D38: Governança e Performance do Portfólio | E38: Eficiência Operacional | F38: Riscos e Incertezas | G38: Integração Organizacional | H38: Maturidade Técnica e Engenharia | I38: Contratos e Cadeia de Fornecimento | J38: Dados, Sistemas e Informação
A39: Governança e Gestão de Portfólio | B39: 12 | C39: 8 | D39: 15 | E39: 10 | F39: 7 | G39: 9 | H39: 2 | I39: 3 | J39: 4
A40: Planejamento Integrado | B40: 14 | C40: 9 | D40: 6 | E40: 11 | F40: 8 | G40: 5 | H40: 3 | I40: 2 | J40: 6
A41: Gestão Contratual e Riscos | B41: 7 | C41: 13 | D41: 5 | E41: 6 | F41: 10 | G41: 4 | H41: 1 | I41: 14 | J41: 2
A42: Suprimentos e Cadeia de Fornecimento | B42: 6 | C42: 11 | D42: 4 | E42: 5 | F42: 7 | G42: 3 | H42: 1 | I42: 12 | J42: 2
A43: Engenharia e Maturidade Técnica | B43: 9 | C43: 6 | D43: 4 | E43: 7 | F43: 8 | G43: 3 | H43: 12 | I43: 2 | J43: 2
A44: Tecnologia e Dados | B44: 5 | C44: 4 | D44: 6 | E44: 7 | F44: 3 | G44: 5 | H44: 2 | I44: 1 | J44: 15

Sheet Lista de Entrevistas_BD
R1: Qtd
B2: # Área | C2: Nível | D2: Nome | E2: E-mail | F2: Área | G2: Cargo | H2: VP | I2: Projetos/Temas | J2: Necessidade | K2: Plataforma | L2: Prioridade de entrevista | M2: Entrevistado Dia | N2: Reagendamentos | O2: Duração | Q2: Necessidade | R2: Rodovias | S2: Trilhos | T2: Corporativo | U2: Total | V2: %
C3: N4 | D3: Gustavo Henrique Lucas Jaquie | E3: gustavo.jaquie@motiva.com.br | F3: Engenharia de Projetos | G3: Gerente Executivo Engenharia Projetos e Centro Expertise | H3: VP Trilhos | I3: Fundamentais para iniciar | J3: Trilhos | K3: 46072.583 | N3: 0.041666667 | O3: 0.041666667 | Q3: Fundamentais para iniciar | R3: =COUNTIFS($J:$J,$Q3,$K:$K,R$2) -> 0 | S3: =COUNTIFS($J:$J,$Q3,$K:$K,S$2) -> 0 | T3: =COUNTIFS($J:$J,$Q3,$K:$K,T$2) -> 0 | U3: =SUM(R3:T3) -> 0 | V3: =R3/$R$6 -> #DIV/0!
C4: N5 | D4: Paulo Cesar Martins Amaral | E4: paulo.amaral@motiva.com.br | F4: Motiva Divisão Mobilidade - Riscos | G4: Consultor Contratos Implantação | H4: VP Trilhos | I4: Fundamentais para iniciar | J4: Trilhos | K4: 46073.375 | N4: 0.041666667 | O4: 0.041666667 | Q4: Importante para aprofundamento | R4: =COUNTIFS($J:$J,$Q4,$K:$K,R$2) -> 0 | S4: =COUNTIFS($J:$J,$Q4,$K:$K,S$2) -> 0 | T4: =COUNTIFS($J:$J,$Q4,$K:$K,T$2) -> 0 | U4: =SUM(R4:T4) -> 0 | V4: =R4/$R$6 -> #DIV/0!
C5: N5 | D5: Paulo Henrique de Almeida Aredes | E5: paulo.aredes@motiva.com.br | F5: Motiva Divisão Mobilidade - Riscos | G5: Consultor Contratos Implantação (L4) | H5: VP Trilhos | I5: Fundamentais para iniciar | J5: Trilhos | K5: 46073.438 | N5: 0.041666667 | O5: 0.041666667 | Q5: Sob Demanda | R5: =COUNTIFS($J:$J,$Q5,$K:$K,R$2) -> 0 | S5: =COUNTIFS($J:$J,$Q5,$K:$K,S$2) -> 0 | T5: =COUNTIFS($J:$J,$Q5,$K:$K,T$2) -> 0 | U5: =SUM(R5:T5) -> 0 | V5: =R5/$R$6 -> #DIV/0!
C6: N5 | D6: Rodrigo Correa de Souza | E6: rodrigo.csouza@motiva.com.br | F6: Motiva Divisão Mobilidade | G6: Consultor Engenharia | H6: VP Trilhos | I6: Fundamentais para iniciar | J6: Trilhos | K6: 46073.562 | N6: 0.041666667 | O6: 0.041666667 | Q6: Total | R6: =SUM(R3:R5) -> 0 | S6: =SUM(S3:S5) -> 0 | T6: =SUM(T3:T5) -> 0 | U6: =SUM(U3:U5) -> 0 | V6: =SUM(V3:V5) -> #DIV/0!
C7: N4 | D7: Rodrigo Mitsuo Kise | E7: rodrigo.kise@motiva.com.br | F7: Motiva Divisão Mobilidade - PMO | G7: Gerente Executivo Empreedimentos e PMO - Projetos Técnicos (L4) | H7: VP Trilhos | I7: Fundamentais para iniciar | J7: Trilhos | K7: 46073.625 | N7: 0.041666667 | O7: 0.041666667
C8: N4 | D8: Emilio Simon Povoa | E8: emilio.povoa@motiva.com.br | F8: Motiva Divisão Mobilidade - Riscos | G8: Gerente Executivo Gerenciamento de Riscos | H8: VP Trilhos | I8: Fundamentais para iniciar | J8: Trilhos | K8: 46073.708 | N8: 0.041666667 | O8: 0.041666667
C9: N5 | D9: Vanilza de Souza Pandolfo | E9: vanilza.pandolfo@motiva.com.br | F9: Motiva Divisão Mobilidade - Riscos | G9: Consultora Riscos Engenharia | H9: VP Trilhos | I9: Importante para aprofundamento | J9: Trilhos | K9: 46076.438 | N9: 0.041666667 | O9: 0.041666667
C10: N5 | D10: William Nascimento Marins | E10: william.marins@motiva.com.br | F10: Motiva Divisão Mobilidade | G10: Gerente de PMO | H10: VP Trilhos | I10: Fundamentais para iniciar | J10: Trilhos | K10: 46076.583 | N10: 0.041666667 | O10: 0.041666667
C11: N4 | D11: Michel Simoes Araujo | E11: michel.araujo@motiva.com.br | F11: Motiva Divisão Mobilidade | G11: Gerente Executivo Acompanhamento de Projetos | H11: VP Trilhos | I11: Importante para aprofundamento | J11: Trilhos | K11: 46076.646 | N11: 0.041666667 | O11: 0.041666667
C12: N6 | D12: Jean Carlos Bonin da Silva | E12: jean.bonin@motiva.com.br | F12: Motiva Divisão Mobilidade | G12: Coordenador PMO | H12: VP Trilhos | I12: Importante para aprofundamento | J12: Trilhos | K12: 46077.458 | N12: 0.041666667 | O12: 0.041666667
C13: N6 | D13: Rebeka Yang Wang | E13: rebeka.wang@motiva.com.br | F13: Motiva Divisão Mobilidade | G13: Coordenadora PMO | H13: VP Trilhos | I13: Importante para aprofundamento | J13: Trilhos | K13: 46077.562 | N13: 0.041666667 | O13: 0.041666667
C14: N3 | D14: Ricardo Alexandre Benicio | E14: ricardo.benicio@motiva.com.br | F14: Motiva Divisão Mobilidade | G14: Diretor Engenharia de Manutenção | H14: VP Trilhos | I14: Fundamentais para iniciar | J14: Trilhos | K14: 46077.688 | N14: 0.041666667 | O14: 0.041666667
C15: N6 | D15: Marcela Alice Ventura Pinto | E15: marcela.ventura@motiva.com.br | F15: Motiva Divisão Mobilidade - PMO | G15: Coordenadora PMO | H15: VP Trilhos | I15: Fundamentais para iniciar | J15: Trilhos | K15: 46078.375 | N15: 0.041666667 | O15: 0.041666667
C16: N5 | D16: Elmo Serejo Pithon Copello | E16: elmo.copello@motiva.com.br | F16: Motiva Divisão Mobilidade - PMO | G16: Gerente Engenharia Empreedimentos | H16: VP Trilhos | I16: Importante para aprofundamento | J16: Trilhos | K16: 46078.646 | N16: 0.041666667 | O16: 0.041666667
C17: N4 | D17: André Luis Teixeira Olveira Freitas | E17: andre.teixeira@motiva.com.br | F17: Motiva Divisão Mobilidade - Riscos | G17: Gerente Executivo Demais Empreedimentos e Rece | H17: VP Trilhos | I17: Fundamentais para iniciar | J17: Trilhos | K17: 46079.583 | N17: 0.041666667 | O17: 0.041666667
C18: N7 | D18: Guilherme Tellis | E18: guilherme.tellis@motiva.com.br | F18: Motiva Divisão Mobilidade | G18: Especialista de PMO | H18: VP Trilhos | I18: Importante para aprofundamento | J18: Trilhos | K18: 46080.583 | N18: 0.041666667 | O18: 0.041666667
C19: N3 | D19: Adriana Martins dos Santos | E19: adriana.santos@motiva.com.br | F19: Engenharia e Implantações - Trilhos | G19: Diretora Engenharia e Implantação | H19: VP Trilhos | I19: Fundamentais para iniciar | J19: Trilhos | K19: 46080.667 | N19: 0.041666667
C20: N5 | D20: Sabrina Santos Pedroso | E20: sabrina.pedroso@motiva.com.br | F20: Riscos Corporativos | G20: Gerente Riscos e Controles | H20: VP Inovação, Tecnologia e Riscos | I20: Fundamentais para iniciar | J20: Corporativo | K20: 46083.458 | N20: 0.027777778
C21: N4 | D21: Luiz Gustavo Degan Franchim | E21: luiz.franchim@motiva.com.br | F21: Suprimentos Gestores Executivos | G21: Gerente Executivo Suprimentos Rodovias | H21: VP Financeiro e Relações Investidores | I21: Fundamentais para iniciar | J21: Corporativo | K21: 46083.625 | N21: 0.027777778
C22: N5 | D22: Juliana Magalhaes Vasconcelos Salomao | E22: juliana.salomao@motiva.com.br | F22: Sustentação | G22: Gerente Gestão Fornecedores e Sustentação | H22: VP Financeiro e Relações Investidores | I22: Fundamentais para iniciar | J22: Corporativo | K22: 46084.562 | N22: 0.027777778
C23: N3 | D23: Danieli Patricia Ribeiro | E23: danieli.ribeiro@motiva.com.br | F23: Assessoria | G23: Assessora Projetos Corporativos | H23: VP Financeiro e Relações Investidores | I23: Fundamentais para iniciar | J23: Corporativo | K23: 46084.625 | N23: 0.027777778
C24: N3 | D24: Angelo Luiz Lodi | E24: angelo.lodi@motiva.com.br | F24: Engenharia e Implantação Rodovias | G24: Diretor de Engenharia e Implantação de Rodovias | H24: VP Rodovias | I24: Fundamentais para iniciar | J24: Rodovias | K24: 46092.458 | N24: 0.041666667 | O24: 0.041666667
C25: N3 | D25: Marcus Vinicius Figur da Rosa | E25: marcus.rosa@motiva.com.br | F25: Financeiro, Desenvolvimento Novos Negócios e Contratos Concessões | G25: Diretor Financeiro, Desenvolvimento Novos Negócios e Contratos Concessões | H25: VP Trilhos | I25: Fundamentais para iniciar | J25: Trilhos | K25: 46093.688 | N25: 0.041666667
C26: N3 | D26: João Pita | E26: joao.pita@motiva.com.br | I26: Importante para aprofundamento | J26: Trilhos | K26: 46094.667 | N26: 0.041666667 | O26: 0.027777778
C27: N5 | D27: Natalia Emy Orita Krutzsch | E27: natalia.krutzsch@motiva.com.br | F27: PMO - PR Vias | G27: Gerente PMO Rodovias | H27: VP Rodovias | I27: Fundamentais para iniciar | J27: Rodovias | K27: 46097.375 | L27: Gabriel, Leticia e Vitor | N27: 0.027777778 | O27: 0.027777778
C28: N4 | D28: Jaime Marlon Silva | E28: jaime.silva@motiva.com.br | F28: Soluções Compartilhadas | G28: Gerente Executivo Soluções Engenharia e Logística | H28: VP Inovação, Tecnologia e Riscos | I28: Fundamentais para iniciar | J28: Corporativo | K28: 46097.583 | L28: Priscila, Sergio e Bruno | N28: 0.027777778 | O28: 0.027777778
C29: N4 | D29: Alexandre Fontes Pereira | E29: alexandre.fontes@motiva.com.br | F29: PMO, Qualidade e Riscos | G29: Gerente Executivo PMO, Qualidade e Riscos | H29: VP Rodovias | I29: Fundamentais para iniciar | J29: Rodovias | K29: 46097.583 | L29: Bella, Le e Vitor | N29: 0.027777778 | O29: 0.027777778
C30: N4 | D30: Romulo Nagumo | E30: romulo.nagumo@motiva.com.br | G30: Gerente Executivo Arquitetura Coporativo | I30: Fundamentais para iniciar | J30: Corporativo | K30: 46097.625 | L30: Bella, Priscila e Sergio | N30: 0.027777778 | O30: 0.027777778
C31: N4 | D31: Marcelo Barbarulo Borgheresi | E31: marcelo.borgheresi@motiva.com.br | F31: Novos Negócios - Sede | G31: Gerente Executivo Desenvolvimento Negócios - Rodovias | H31: VP Rodovias | I31: Fundamentais para iniciar | J31: Rodovias | K31: 46097.667 | L31: Vitor, Sergio e Gabriel | N31: 0.027777778 | O31: 0.027777778
C32: N4 | D32: Heloisa Helena de Oliveira Tormin Chaer | E32: heloisa.chaer@motiva.com.br | F32: Planejamento e Governança | G32: Gerente Executiva Planejamento e Governança | H32: VP Inovação, Tecnologia e Riscos | I32: Fundamentais para iniciar | J32: Corporativo | K32: 46097.688 | L32: Priscila, Bella e Ana Cris | N32: 0.027777778 | O32: 0.027777778
C33: N5 | D33: Karina Baungartner | E33: karina.baungartner@motiva.com.br | F33: PMO - Rio SP | G33: Gerente PMO Rodovias | H33: VP Rodovias | I33: Fundamentais para iniciar | J33: Rodovias | K33: 46098.396 | L33: Bella, Le e Gabriel | N33: 0.027777778 | O33: 0.027777778
C34: N5 | D34: Anderson Aparecido Zanetti | E34: anderson.zanetti@motiva.com.br | F34: PMO, Qualidade e Riscos | G34: Consultor PMO | H34: VP Rodovias | I34: Fundamentais para iniciar | J34: Rodovias | K34: 46098.417 | L34: Priscila e Ana Cris | N34: 0.027777778 | O34: 0.027777778
C35: N5 | D35: Lucas Giraldi Rapchan Aguilar | E35: lucas.aguilar@motiva.com.br | F35: PMO Rodovias | G35: Gerente PMO Rodovias | H35: VP Rodovias | I35: Fundamentais para iniciar | J35: Rodovias | K35: 46098.458 | L35: Vitor e Gabriel | N35: 0.027777778 | O35: 0.027777778
C36: N4 | D36: Jorge Rangel Maia | E36: jorge.maia@motiva.com.br | F36: Suprimentos Gestores Executivos | G36: Gerente Executivo Suprimentos Mobilidade e Aero | H36: VP Financeiro e Relações Investidores | I36: Importante para aprofundamento | J36: Corporativo | K36: 46098.583 | L36: Priscila e Ana Cris | N36: 0.027777778 | O36: 0.027777778
C37: N3 | D37: Josiane Carvalho de Almeida | E37: josiane.almeida@motiva.com.br | F37: Planejamento, Gestão Financeira e Novos Negócios | G37: Diretora Financeira e Desenvolvimento Negócios | H37: VP Rodovias | I37: Fundamentais para iniciar | J37: Rodovias | K37: 46098.583 | L37: Vitor, Bella e Thiago | M37: 46098 | N37: 0.027777778 | O37: 0.027777778
C38: N6 | D38: Thiago Siqueira de Lima | E38: thiago.siqueira@motiva.com.br | F38: Arquitetura | G38: Arquiteto Corporativo | H38: VP Inovação, Tecnologia e Riscos | I38: Importante para aprofundamento | J38: Corporativo | K38: 46098.667 | L38: Priscila, Sergio e Ana Cris | N38: 0.027777778 | O38: 0.027777778
C39: N4 | D39: Michele Janaina Dick Romano | E39: michele.romano@motiva.com.br | F39: Jurídico Contencioso Estratégico | G39: Gerente Executiva Jurídico | H39: VP Finanças e Relações Investidores | I39: Fundamentais para iniciar | J39: Corporativo | K39: 46098.708 | L39: Priscila e Vitor | N39: 0.027777778 | O39: 0.027777778
C40: N6 | D40: Patricia Muller Ramos Kusdra | E40: patricia.kusdra@motiva.com.br | F40: Gestão Financeira e Seguros | G40: Coordenadora Recebimento Integrado e Contas a pagar | H40: VP Finanças e Relações Investidores | I40: Importante para aprofundamento | J40: Corporativo | K40: 46098.708 | L40: Gabriel, Leticia e Ana Cris | N40: 0.027777778 | O40: 0.027777778
C41: N6 | D41: Ana Laura Marocolo Marigo | E41: ana.marigo@motiva.com.br | F41: PMO - Via Oeste | G41: Coordenadora PMO | H41: VP Rodovias | I41: Fundamentais para iniciar | J41: Rodovias | K41: 46099.375 | L41: Gabriel, Leticia e Ana Cris | N41: 0.027777778 | O41: 0.027777778
C42: N4 | D42: Tiago Terra Esteves | E42: tiago.esteves@motiva.com.br | G42: Gerente Executivo de Desenvolvimento de Novos Negocios - Trilhos | I42: Importante para aprofundamento | J42: Trilhos | K42: 46099.542 | L42: Vitor, Sergio e Gabriel | N42: 0.027777778 | O42: 0.027777778
C43: N4 | D43: Jorge Manuel Goncalves Pereira | E43: jorge.pereira@motiva.com.br | F43: Operações | G43: Gerente Executivo Estratégia de Operações | H43: VP Rodovias | I43: Importante para aprofundamento | J43: Rodovias | K43: 46099.583 | L43: Vitor e Priscila | N43: 0.027777778 | O43: 0.027777778
C44: N5 | D44: Cesar Sampaio de Castro | E44: cesar.sampaio@motiva.com.br | F44: Gestão Portfólio e Valor | G44: Gerente Gestão Portfólio e Valor | H44: VP Inovação, Tecnologia e Riscos | I44: Fundamentais para iniciar | J44: Corporativo | K44: 46099.625 | L44: Gabriel, Sergio e Vitor | N44: 0.027777778 | O44: 0.027777778
C45: N5 | D45: Tassiano Sobot Ornellas | E45: tassiano.ornellas@motiva.com.br | F45: Segurança do Trabalho | G45: Gerente Executivo Segurança do Trabalho | H45: VP Rodovias | I45: Importante para aprofundamento | J45: Rodovias | K45: 46099.667 | L45: Gabriel, Bella e Vitor | N45: 0.041666667 | O45: 0.027777778
C46: N4 | D46: Keller Alves Rodrigues | E46: keller.junior@motiva.com.br | F46: Unidade de Negócio - PR Vias | G46: Diretor Unidade de Negócio - PR Vias | H46: VP Rodovias | I46: Fundamentais para iniciar | J46: Rodovias | K46: 46100.375 | N46: 0.041666667 | O46: 0.027777778
C47: N4 | D47: Afranio Nogueira Magalhaes | E47: afranio.magalhaes@motiva.com.br | F47: Engenharia e Implantação - Sorocabana | G47: Gerente Executivo Engenharia e Obras | H47: VP Rodovias | I47: Fundamentais para iniciar | J47: Rodovias | K47: 46100.458 | N47: 0.027777778 | O47: 0.027777778
C48: N6 | D48: Juliana Ming Martini Naressi | E48: juliana.ming@motiva.com.br | F48: Gestão Compras Sustentáveis | G48: Coordenador Compras Sustentáveis | H48: VP Financeiro e Relações Investidores | I48: Importante para aprofundamento | J48: Corporativo | K48: 46100.583 | L48: Priscila e Ana Cris | N48: 0.027777778 | O48: 0.027777778
C49: N3 | D49: Fausto Camilotti | E49: fausto.camilotti@motiva.com.br | F49: Negócio Rodovias | G49: Diretor de Operações - Rodovia | H49: VP Rodovias | I49: Fundamentais para iniciar | J49: Rodovias | K49: 46100.583 | N49: 0.041666667 | O49: 0.027777778
C50: N4 | D50: Ricardo da Costa | E50: ricardo.costa@motiva.com.br | F50: Gestão Financeira e Seguros | G50: Gerente Executivo Financeiro e Seguros | H50: VP Finanças e Relações Investidores | I50: Fundamentais para iniciar | J50: Corporativo | K50: 46100.625 | L50: Bella, Leticia e Ana Cris | N50: 0.027777778 | O50: 0.027777778
C51: N4 | D51: Nelson Soares Neto | E51: nelson.neto@motiva.com.br | F51: Unidade de Negócio - MS Via | G51: Diretor Unidade de Negócio - MS Via | H51: VP Rodovias | I51: Fundamentais para iniciar | J51: Rodovias | K51: 46100.625 | N51: 0.041666667 | O51: 0.027777778
C52: N7 | D52: Maria Leticia Palmieri Jaco | E52: maria.jaco@motiva.com.br | F52: Req to Pay | G52: Supervisora recebimento fiscal | H52: VP Finanças e Relações Investidores | I52: Importante para aprofundamento | J52: Corporativo | K52: 46100.667 | L52: Sérgio e Ana Cris | N52: 0.027777778 | O52: 0.027777778
C53: N6 | D53: Thais Souza Liberato Leandro | E53: thais.leandro@motiva.com.br | F53: Riscos Engenharia | G53: Coordenadora de Riscos Engenharia | H53: VP Rodovias | I53: Fundamentais para iniciar | J53: Rodovias | K53: 46100.667 | N53: 0.027777778 | O53: 0.027777778
C54: N6 | D54: Carolina Cerdeira | E54: carolina.goes@motiva.com.br | F54: Facilities, Viagens e Reembolsos | G54: Coordenadora Facilities, Viagens e Reembolsos | H54: VP Finanças e Relações Investidores | I54: Fundamentais para iniciar | J54: Corporativo | K54: 46101.417 | L54: Priscila e Ana Cris | O54: 0.027777778
C55: N5 | D55: Jhonnathan Preisner de Souza | E55: jhonnathan.souza@motiva.com.br | F55: Pavimentos | G55: Gerente Pavimentos | H55: VP Rodovias | I55: Importante para aprofundamento | J55: Rodovias | K55: 46101.458 | L55: Gabriel e Ana Cris | N55: 0.027777778 | O55: 0.027777778
C56: N4 | D56: Fabio Portela Rodrigues | E56: fabio.portela@motiva.com.br | F56: Soluções Mobilidade | G56: Gerente Executivo Soluções de Mobilidade | H56: VP Inovação, Tecnologia e Riscos | I56: Fundamentais para iniciar | J56: Corporativo | K56: 46101.583 | L56: Gabriel e Ana Cris | N56: 0.027777778 | O56: 0.027777778
C57: N4 | D57: Artur Henrique Evangelista Carvalho | E57: artur.carvalho@motiva.com.br | F57: Engenharia | G57: Gerente Executivo Engenharia | H57: VP Rodovias | I57: Fundamentais para iniciar | J57: Rodovias | K57: 46101.583 | L57: Vitor e Lê | N57: 0.027777778 | O57: 0.027777778
C58: N4 | D58: Gabriel Bittencourt Jacondino | E58: gabriel.jacondino@motiva.com.br | F58: Finanças e Desenvolvimento de Negócios | G58: Gerente Executivo Contratos Concessões Mobilidade | H58: VP Trilhos | I58: Importante para aprofundamento | J58: Trilhos | K58: 46101.667 | L58: Priscila e Ana Cris | N58: 0.027777778 | O58: 0.027777778
C59: N4 | D59: Cleber Chinelato | E59: cleber.chinelato@motiva.com.br | F59: SOLUCOES RODOVIAS | G59: Gerente Executivo Soluções de Rodovias | H59: Fundamentais para iniciar | I59: Fundamentais para iniciar | J59: Rodovias | K59: 46105.625 | L59: Bella, Le e Vitor | N59: 0.027777778 | O59: 0.027777778
C60: N5 | D60: Fabiana Abrita Argentin | E60: fabiana.abrita@motiva.com.br | F60: Núcleo de Capex | G60: Consultora Perfomance Negocio | H60: VP Financeiro e Relações Investidores | I60: Fundamentais para iniciar | J60: Corporativo | K60: 46106.604 | L60: Bella, Vitor e Le | N60: 0.041666667 | O60: 0.027777778
C61: N7 | D61: Leticia Cardoso | E61: leticia.cardoso@motiva.com.br | F61: Núcleo de Capex | G61: Analista Capex Jr | H61: VP Financeiro e Relações Investidores | I61: Fundamentais para iniciar | J61: Corporativo | K61: 46106.646 | L61: Bella, Vitor e Le | N61: 0.041666667 | O61: 0.027777778
C62: N4 | D62: Alexandro Marcelo Zopolato Francisco | E62: alexandro.francisco@motiva.com.br | F62: Engenharia e Implantação - PR Vias | G62: Gerente Executivo Engenharia e Obras | H62: VP Rodovias | I62: Fundamentais para iniciar | J62: Rodovias | K62: 46106.667 | L62: Pri e Ana Cris | N62: 0.027777778 | O62: 0.027777778
C63: N3 | D63: Flavio Roberto Dornelas Camara Pimentel | E63: flavio.pimentel@motiva.com.br | F63: Núcleo de Capex | G63: Diretor do Nucleo de Capex | H63: VP Financeiro e Relações Investidores | I63: Fundamentais para iniciar | J63: Corporativo | K63: 46107.458 | N63: 0.041666667 | O63: 0.027777778
C64: N5 | D64: Alexandre David Magno | E64: alexandre.magno@motiva.com.br | F64: Núcleo de Capex | G64: Consultor Riscos Operacionais Capex | H64: VP Financeiro e Relações Investidores | I64: Fundamentais para iniciar | J64: Corporativo | K64: 46107.5 | L64: Bella, Vitor e Le | N64: 0.041666667
C65: N2 | D65: Pedro Paulo Archer Sutter | E65: pedro.sutter@motiva.com.br | F65: Sustentabilidade, Riscos e Compliace | G65: Diretor Vice Presidente Inovação, Tecnologia e Riscos | H65: VP Inovação, Tecnologia e Riscos | I65: Fundamentais para iniciar | J65: Corporativo | K65: 46107.583 | L65: Bella, Vitor e Le | N65: 0.041666667
C66: N5 | D66: Giancarlo Ferreira | E66: giancarlo.ferreira@motiva.com.br | F66: Gestão Serviços e Atendimento | G66: Gerente Custos e Orçamento | H66: VP Finanças e Relações Investidores | I66: Importante para aprofundamento | J66: Corporativo | K66: 46108.458 | L66: Bella, Ana Cris e Lê | N66: 0.027777778
C67: N5 | D67: Douglas Pereira de Oliveira Ribeiro | E67: douglas.ribeiro@motiva.com.br | F67: Relações Investidores | G67: Consultor Relações Investidores | H67: VP Financeiro e Relações Investidores | I67: Sob Demanda | J67: Corporativo | K67: 46111.583 | L67: Pri, Gabriel e Sergio | N67: 0.027777778
C68: N6 | D68: Camila Gil Henriques Marinheiro | E68: camila.marinheiro@motiva.com.br | F68: Tecnologia e Digital | G68: Coordenadora Soluções Engenharia | H68: VP Inovação, Tecnologia e Riscos | I68: Fundamentais para iniciar | J68: Corporativo | K68: 46111.583 | L68: Vitor, Bella e Guilherme | N68: 0.027777778
C69: N3 | D69: Flavia Godoy de Carvalho E Silva | E69: flavia.godoy@motiva.com.br | F69: Relações Investidores | G69: Diretora de Relação Investidores | H69: VP Financeiro e Relações Investidores | I69: Fundamentais para iniciar | J69: Corporativo | K69: 46112.583 | L69: Vitor e Thiago | N69: 0.027777778
C70: N5 | D70: Lucas Tadeu Souza de Araujo | E70: lucas.tadeu@motiva.com.br | F70: Gestão de Frotas | G70: Gerente de Frota | H70: VP Finanças e Relações Investidores | I70: Importante para aprofundamento | J70: Corporativo | K70: 46113.583 | L70: Bella, Ana Cris e Lê | N70: 0.027777778
C71: N3 | D71: Ronan Pedroso Nogueira Gaeti | E71: ronan.gaeti@motiva.com.br | F71: Soluções Compartilhadas | G71: Diretor de Soluções Compartilhadas | H71: VP Inovação, Tecnologia e Riscos | I71: Importante para aprofundamento | J71: Corporativo | K71: 46113.583 | L71: Thiago | N71: 0.027777778
C72: N3 | D72: Marcelo Cordeiro Ferraz | E72: marcelo.ferraz@motiva.com.br | F72: Supply Chain | G72: Diretor de Supply Chain | H72: VP Financeiro e Relações Investidores | I72: Fundamentais para iniciar | J72: Corporativo | K72: 46114.417 | L72: Thiago | N72: 0.027777778
C73: N3 | D73: Priscila Aparecida Rodrigues Martins | E73: priscila.martins@motiva.com.br | F73: Riscos e Controle | G73: Diretora Riscos e Controles Internos | H73: VP Inovação, Tecnologia e Riscos | I73: Fundamentais para iniciar | J73: Corporativo | K73: 46114.667 | L73: Thiago | N73: 0.027777778
C74: N2 | D74: Eduardo Siqueira Moraes Camargo | E74: eduardo.camargo@motiva.com.br | F74: Rodovias | G74: Vice Presidente Negócios Rodovias | H74: VP Rodovias | I74: Fundamentais para iniciar | J74: Rodovias | K74: 46121.667 | L74: Thiago | N74: 0.041666667
C75: N5 | D75: Camila Mendonca Rabassa Chanquini | E75: camila.rabassa@motiva.com.br | F75: Motiva Divisão Mobilidade - PMO | G75: Gerente Engenharia e Projetos Civil e Qualidade | H75: VP Trilhos | I75: Sob Demanda | J75: Trilhos | K75: Licença a Maternidade
C76: N2 | D76: Waldo Edwin Perez Leskovar | E76: waldo.perez@motiva.com.br | F76: Financeiro e Relação de Investidores | G76: Diretor Vice Presidente Financeiro e Relações Investidores | H76: VP Financeiro e Relações Investidores | I76: Fundamentais para iniciar | J76: Corporativo
C77: N5 | D77: Ramon Marcelo Araujo dos Santos | E77: ramon.araujo@motiva.com.br | F77: Compras Rodovias I | G77: Gerente Suprimentos Rodovias | H77: VP Financeiro e Relações Investidores | I77: Sob Demanda | J77: Corporativo
C78: N5 | D78: Rodrigo Luiz Correia | E78: rodrigo.lcorrea@motiva.com.br | G78: Gerente Planejamento Logistico | H78: VP Financeiro e Relações Investidores | I78: Sob Demanda | J78: Corporativo
C79: N3 | D79: Jose Garibalde Prata Freitas Filho | E79: jose.garibalde@motiva.com.br | F79: CSC | G79: Diretor CSC | H79: VP Finanças e Relações Investidores | I79: Fundamentais para iniciar | J79: Corporativo
C80: N5 | D80: Thais Aparecida de Faria | E80: thais.faria@motiva.com.br | F80: Facilities | G80: Gerente de Facilities | H80: VP Finanças e Relações Investidores | I80: Sob Demanda | J80: Corporativo
C81: N2 | D81: Rodrigo Araujo Alves | E81: rodrigoaraujo.alves@motiva.com.br | F81: Finanças e Relações Investidores | G81: Diretor Vice Presidente Finanças e Relações Investidores | H81: VP Finanças e Relações Investidores | I81: Sob Demanda | J81: Corporativo
C82: N3 | D82: Carl Douglas | E82: carl.douglas@motiva.com.br | F82: Contabilidade Estratégica | G82: Diretor de Contabilidade Estratégica | H82: VP Financeiro e Relações Investidores | I82: Sob Demanda | J82: Corporativo
C83: N3 | D83: Felipe Harari Valente | E83: felipe.valente@motiva.com.br | F83: Tesouraria e Financeiro | G83: Diretor de Tesouraria e Financeiro | H83: VP Financeiro e Relações Investidores | I83: Sob Demanda | J83: Corporativo
C84: N6 | D84: Caue Esteves Cunha | E84: caue.cunha@motiva.com.br | F84: Relações Investidores | G84: Especialista Relações Investidores | H84: VP Financeiro e Relações Investidores | I84: Sob Demanda | J84: Corporativo
C85: N4 | D85: Luciana Irene de Lima e Silva | E85: luciana.irene@motiva.com.br | F85: Planejamento e Controle | G85: Gerente Executiva Planejamento Corporativo | H85: VP Finanças e Relações Investidores | I85: Sob Demanda | J85: Corporativo
C86: N2 | D86: Raquel Cardoso da Silva | E86: raquel.cardoso@motiva.com.br | F86: Pessoas e Desenvolvimento Organizacional | G86: Diretora Vice Presidente Pessoas, Desenvolvimento Organizacional | H86: VP Pessoas, Desenvolvimento Organizacional | I86: Sob Demanda | J86: Corporativo
C87: N4 | D87: Rafael Antonio Bortolotti | E87: rafael.bortolotti@motiva.com.br | F87: Desenvolvimento Organizacional | G87: Gerente Executivo Desenvolvimento Organizacional | H87: VP Pessoas, Desenvolvimento Organizacional | I87: Sob Demanda | J87: Corporativo
C88: N5 | D88: Priscila Rodrigues Pereira | E88: priscila.pereira@motiva.com.br | F88: Desenvolvimento Organizacional | G88: Gerente Workface Planning e Design Organizacional | H88: VP Pessoas, Desenvolvimento Organizacional | I88: Sob Demanda | J88: Corporativo
C89: N6 | D89: Carine Menezes de Andrade | E89: carine.andrade@motiva.com.br | F89: Desenvolvimento Organizacional | G89: Especialista Planejamento Força de Trabalho | H89: VP Pessoas, Desenvolvimento Organizacional | I89: Sob Demanda | J89: Corporativo
C90: N6 | D90: Juliana de Freitas | E90: juliana.freitas@motiva.com.br | F90: Desenvolvimento Organizacional | G90: Especialista Projetos e Processos | H90: VP Pessoas, Desenvolvimento Organizacional | I90: Sob Demanda | J90: Trilhos
... C98: N3 | D98: Fabio Mota | E98: fabio.mota@motiva.com.br | F98: Tecnologia e Digital | G98: Diretora de Tecnologia e Digital/CTO | H98: VP Inovação, Tecnologia e Riscos | I98: Fundamentais para iniciar | J98: Corporativo
C99: N6 | D99: Eslon Sousa | F99: Tecnologia e Digital | G99: Especialista Tecnologia e Digital | I99: Sob Demanda
C100: N5 | D100: Thiago Chacon Codesseira | F100: Riscos Corporativos | G100: Gerente Precificação Riscos | J100: Corporativo | O100: 0.041666667
C101: N3 | D101: Francine Nunes Saueia Keterer | E101: francine.saueia@motiva.com.br | F101: Estratégia e Inovação | G101: Diretora Estratégia e Inovação | H101: VP Inovação, Tecnologia e Riscos | I101: Fundamentais para iniciar | J101: Corporativo | O101: 0.041666667
C102: N5 | D102: Murilo Massaretto | E102: murilo.massaretto@motiva.com.br | F102: Estrategia e Inovação | G102: Consultor Inovação | H102: VP Inovação, Tecnologia e Riscos | I102: Sob Demanda | J102: Corporativo
C103: N5 | D103: Emilia Guerra Dias | E103: emilia.dias@motiva.com.br | F103: Estrategia e Inovação | G103: Consultora Estratégia e Inovação | H103: VP Inovação, Tecnologia e Riscos | I103: Sob Demanda | J103: Corporativo
C104: N2 | D104: Andre Gustavo Salcedo Teixeira Mendes | E104: andre.salcedo@motiva.com.br | F104: Trilhos | G104: Diretor Vice Presidente Negócios - Trilhos | H104: VP Trilhos | I104: Fundamentais para iniciar | J104: Trilhos
C105: N3 | D105: Juliana Criscuolo | E105: juliana.criscoulo@motiva.com.br | I105: Sob Demanda | J105: Trilhos | M105: *surgiu após mapeamento de interfaces
C106: N5 | D106: Luciana Bugno Alves de Araujo | E106: luciana.bugno@motiva.com.br | G106: Consultora de Riscos | I106: Sob Demanda | J106: Trilhos | M106: *surgiu após mapeamento de interfaces
C107: N4 | D107: Igor Camilo | E107: igor.camillo@motiva.com.br | F107: MOTIVA DIVISAO MOBILIDADE - ADMINISTRACAO E FINANC | G107: GERENTE EXECUTIVO(A) PLANEJAMENTO E GESTAO FINA | H107: VP Trilhos | I107: Sob Demanda | J107: Trilhos | M107: *surgiu após mapeamento de interfaces
...
